<?xml version="1.0" encoding="utf-8"?>
<Book Count="1">
	<Sheet Name="スタッフ" Count="1419">
		<Header>
			<Param Name="出力先" Ident="Out" Type="PublicFile" Min="" Max="" Chg="" />
			<Param Name="種類" Ident="Type" Type="s8" Min="" Max="" Chg="" />
			<Param Name="テキスト1" Ident="Text1" Type="string" Min="" Max="" Chg="" />
			<Param Name="テキスト2" Ident="Text2" Type="string" Min="" Max="" Chg="" />
			<Param Name="テキスト3" Ident="Text3" Type="string" Min="" Max="" Chg="" />
		</Header>
		<Data>
			<Param Out="" Type="1" Text1="Producer" Text2="" Text3="" />
			<Param Out="" Type="2" Text1="" Text2="Masahiro Higuchi" Text3="" />
			<Param Out="" Type="11" Text1="" Text2="" Text3="" />
			<Param Out="" Type="1" Text1="Producer" Text2="" Text3="" />
			<Param Out="" Type="2" Text1="" Text2="Genki Yokota" Text3="" />
			<Param Out="" Type="2" Text1="" Text2="Toyokazu Nonaka" Text3="" />
			<Param Out="" Type="11" Text1="" Text2="" Text3="" />
			<Param Out="" Type="1" Text1="Sub Producer" Text2="" Text3="" />
			<Param Out="" Type="2" Text1="" Text2="Kohei Maeda" Text3="" />
			<Param Out="" Type="11" Text1="" Text2="" Text3="" />
			<Param Out="" Type="1" Text1="Director" Text2="" Text3="" />
			<Param Out="" Type="2" Text1="" Text2="Tsutomu Tei" Text3="" />
			<Param Out="" Type="11" Text1="" Text2="" Text3="" />
			<Param Out="" Type="1" Text1="Director" Text2="" Text3="" />
			<Param Out="" Type="2" Text1="" Text2="Kenta Nakanishi" Text3="" />
			<Param Out="" Type="11" Text1="" Text2="" Text3="" />
			<Param Out="" Type="1" Text1="Coordinator" Text2="" Text3="" />
			<Param Out="" Type="2" Text1="" Text2="Misaki Hiraga" Text3="" />
			<Param Out="" Type="12" Text1="" Text2="" Text3="" />
			<Param Out="" Type="1" Text1="Main Character Designer &amp; Illustration" Text2="" Text3="" />
			<Param Out="" Type="2" Text1="" Text2="Mika Pikazo" Text3="" />
			<Param Out="" Type="10" Text1="" Text2="" Text3="" />
			<Param Out="" Type="1" Text1="Concept Art" Text2="" Text3="" />
			<Param Out="" Type="2" Text1="" Text2="Kazuma Koda" Text3="" />
			<Param Out="" Type="10" Text1="" Text2="" Text3="" />
			<Param Out="" Type="1" Text1="Character Design Assistant" Text2="" Text3="" />
			<Param Out="" Type="2" Text1="" Text2="Amagaitaro (ORDAN)" Text3="" />
			<Param Out="" Type="12" Text1="" Text2="" Text3="" />
			<Param Out="" Type="1" Text1="Scenario Director" Text2="" Text3="" />
			<Param Out="" Type="2" Text1="" Text2="Nami Komuro" Text3="" />
			<Param Out="" Type="11" Text1="" Text2="" Text3="" />
			<Param Out="" Type="1" Text1="Planning Director" Text2="" Text3="" />
			<Param Out="" Type="2" Text1="" Text2="Yuya Ishii" Text3="" />
			<Param Out="" Type="11" Text1="" Text2="" Text3="" />
			<Param Out="" Type="1" Text1="Art Director" Text2="" Text3="" />
			<Param Out="" Type="2" Text1="" Text2="Takafumi Teraoka" Text3="" />
			<Param Out="" Type="11" Text1="" Text2="" Text3="" />
			<Param Out="" Type="1" Text1="Programming Director" Text2="" Text3="" />
			<Param Out="" Type="2" Text1="" Text2="Susumu Ishihara" Text3="" />
			<Param Out="" Type="11" Text1="" Text2="" Text3="" />
			<Param Out="" Type="1" Text1="Sound Director" Text2="" Text3="" />
			<Param Out="" Type="2" Text1="" Text2="Yasuhisa Baba" Text3="" />
			<Param Out="" Type="11" Text1="" Text2="" Text3="" />
			<Param Out="" Type="1" Text1="Art Design Lead" Text2="" Text3="" />
			<Param Out="" Type="2" Text1="" Text2="Hiromi Tanaka" Text3="" />
			<Param Out="" Type="10" Text1="" Text2="" Text3="" />
			<Param Out="" Type="1" Text1="Art Design" Text2="" Text3="" />
			<Param Out="" Type="4" Text1="" Text2="Paul Patrashcu 　" Text3="" />
			<Param Out="" Type="4" Text1="" Text2="Yuta Morikawa" Text3="" />
			<Param Out="" Type="4" Text1="" Text2="Yuka Tokuda" Text3="" />
			<Param Out="" Type="10" Text1="" Text2="" Text3="" />
			<Param Out="" Type="1" Text1="Game Planner" Text2="" Text3="" />
			<Param Out="" Type="4" Text1="" Text2="Shiori Minari" Text3="" />
			<Param Out="" Type="4" Text1="" Text2="Ryuichiro Kouguchi" Text3="" />
			<Param Out="" Type="4" Text1="" Text2="Kuniyoshi Tanaka" Text3="" />
			<Param Out="" Type="4" Text1="" Text2="Miwa Kashu" Text3="" />
			<Param Out="" Type="4" Text1="" Text2="Hidemi Yamaguchi" Text3="" />
			<Param Out="" Type="4" Text1="" Text2="Hidenobu Nozoe" Text3="" />
			<Param Out="" Type="10" Text1="" Text2="" Text3="" />
			<Param Out="" Type="1" Text1="Text Support" Text2="" Text3="" />
			<Param Out="" Type="2" Text1="" Text2="Naoya Inui" Text3="" />
			<Param Out="" Type="10" Text1="" Text2="" Text3="" />
			<Param Out="" Type="1" Text1="UI Art Lead" Text2="" Text3="" />
			<Param Out="" Type="2" Text1="" Text2="Shioe Ohashi" Text3="" />
			<Param Out="" Type="10" Text1="" Text2="" Text3="" />
			<Param Out="" Type="1" Text1="UI Art" Text2="" Text3="" />
			<Param Out="" Type="4" Text1="" Text2="Kinuka Watanabe" Text3="" />
			<Param Out="" Type="4" Text1="" Text2="Eiko Hirao" Text3="" />
			<Param Out="" Type="4" Text1="" Text2="Xu Hengrui" Text3="" />
			<Param Out="" Type="10" Text1="" Text2="" Text3="" />
			<Param Out="" Type="1" Text1="Sprite Art" Text2="" Text3="" />
			<Param Out="" Type="2" Text1="" Text2="Naotaka Ohnishi" Text3="" />
			<Param Out="" Type="10" Text1="" Text2="" Text3="" />
			<Param Out="" Type="1" Text1="Character Art Lead" Text2="" Text3="" />
			<Param Out="" Type="2" Text1="" Text2="Makoto Onogi" Text3="" />
			<Param Out="" Type="10" Text1="" Text2="" Text3="" />
			<Param Out="" Type="1" Text1="Character Art" Text2="" Text3="" />
			<Param Out="" Type="4" Text1="" Text2="Rintaro Sakihara" Text3="" />
			<Param Out="" Type="4" Text1="" Text2="Mana Ogawa" Text3="" />
			<Param Out="" Type="4" Text1="" Text2="Hina Watanabe" Text3="" />
			<Param Out="" Type="4" Text1="" Text2="Yuka Tokuda" Text3="" />
			<Param Out="" Type="4" Text1="" Text2="Yuka Nishiyama" Text3="" />
			<Param Out="" Type="4" Text1="" Text2="Rikako Hiraoka" Text3="" />
			<Param Out="" Type="4" Text1="" Text2="Manae Kiyomiya" Text3="" />
			<Param Out="" Type="10" Text1="" Text2="" Text3="" />
			<Param Out="" Type="1" Text1="Character Animation" Text2="" Text3="" />
			<Param Out="" Type="3" Text1="" Text2="Takafumi Teraoka" Text3="" />
			<Param Out="" Type="3" Text1="" Text2="Yumi Akachi" Text3="" />
			<Param Out="" Type="10" Text1="" Text2="" Text3="" />
			<Param Out="" Type="1" Text1="Facial Animation" Text2="" Text3="" />
			<Param Out="" Type="2" Text1="" Text2="Yuka Nishiyama" Text3="" />
			<Param Out="" Type="10" Text1="" Text2="" Text3="" />
			<Param Out="" Type="1" Text1="Environment Art Lead" Text2="" Text3="" />
			<Param Out="" Type="2" Text1="" Text2="Misato Ukai" Text3="" />
			<Param Out="" Type="10" Text1="" Text2="" Text3="" />
			<Param Out="" Type="1" Text1="Environment Art" Text2="" Text3="" />
			<Param Out="" Type="4" Text1="" Text2="Shigeki Osaka" Text3="" />
			<Param Out="" Type="4" Text1="" Text2="Remi Nakano" Text3="" />
			<Param Out="" Type="4" Text1="" Text2="Yuta Maeno" Text3="" />
			<Param Out="" Type="4" Text1="" Text2="Vo Phuong Anh" Text3="" />
			<Param Out="" Type="4" Text1="" Text2="Youhei Kubotsu" Text3="" />
			<Param Out="" Type="4" Text1="" Text2="Yuki Oka" Text3="" />
			<Param Out="" Type="10" Text1="" Text2="" Text3="" />
			<Param Out="" Type="1" Text1="VFX Lead" Text2="" Text3="" />
			<Param Out="" Type="2" Text1="" Text2="Koki Uchimura" Text3="" />
			<Param Out="" Type="10" Text1="" Text2="" Text3="" />
			<Param Out="" Type="1" Text1="VFX" Text2="" Text3="" />
			<Param Out="" Type="2" Text1="" Text2="Rikako Hiraoka" Text3="" />
			<Param Out="" Type="10" Text1="" Text2="" Text3="" />
			<Param Out="" Type="1" Text1="Programmer" Text2="" Text3="" />
			<Param Out="" Type="4" Text1="" Text2="Takafumi Kaneko" Text3="" />
			<Param Out="" Type="4" Text1="" Text2="Yusuke Shibata" Text3="" />
			<Param Out="" Type="4" Text1="" Text2="Yusuke Murakami" Text3="" />
			<Param Out="" Type="4" Text1="" Text2="Naoki Habu" Text3="" />
			<Param Out="" Type="4" Text1="" Text2="Hiroaki Terada" Text3="" />
			<Param Out="" Type="4" Text1="" Text2="Kaoru Morita" Text3="" />
			<Param Out="" Type="4" Text1="" Text2="Takamasa Mizoro" Text3="" />
			<Param Out="" Type="4" Text1="" Text2="Ryo Date" Text3="" />
			<Param Out="" Type="4" Text1="" Text2="Tatsuya Sengoku" Text3="" />
			<Param Out="" Type="4" Text1="" Text2="Tetsuya Satoh" Text3="" />
			<Param Out="" Type="4" Text1="" Text2="Yu Yamanaka" Text3="" />
			<Param Out="" Type="4" Text1="" Text2="He Rongshan" Text3="" />
			<Param Out="" Type="4" Text1="" Text2="Koichiro Naruse" Text3="" />
			<Param Out="" Type="4" Text1="" Text2="Junya Kadono" Text3="" />
			<Param Out="" Type="4" Text1="" Text2="Ryoma Yamauchi" Text3="" />
			<Param Out="" Type="4" Text1="" Text2="Moe Ando" Text3="" />
			<Param Out="" Type="4" Text1="" Text2="Ikuya Shimada" Text3="" />
			<Param Out="" Type="10" Text1="" Text2="" Text3="" />
			<Param Out="" Type="1" Text1="Technical Programmer" Text2="" Text3="" />
			<Param Out="" Type="4" Text1="" Text2="Kei Nakashima" Text3="" />
			<Param Out="" Type="4" Text1="" Text2="Junko Tanaka" Text3="" />
			<Param Out="" Type="4" Text1="" Text2="Kanako Hiroi" Text3="" />
			<Param Out="" Type="10" Text1="" Text2="" Text3="" />
			<Param Out="" Type="1" Text1="Lead Composer" Text2="" Text3="" />
			<Param Out="" Type="2" Text1="" Text2="Yasuhisa Baba" Text3="" />
			<Param Out="" Type="10" Text1="" Text2="" Text3="" />
			<Param Out="" Type="1" Text1="Composer &amp; Recording" Text2="" Text3="" />
			<Param Out="" Type="2" Text1="" Text2="Kazuki Komai" Text3="" />
			<Param Out="" Type="10" Text1="" Text2="" Text3="" />
			<Param Out="" Type="1" Text1="Composer &amp; Mastering Engineer" Text2="" Text3="" />
			<Param Out="" Type="2" Text1="" Text2="Hiroki Morishita" Text3="" />
			<Param Out="" Type="10" Text1="" Text2="" Text3="" />
			<Param Out="" Type="1" Text1="Composer" Text2="" Text3="" />
			<Param Out="" Type="2" Text1="" Text2="Takeru Kanazaki" Text3="" />
			<Param Out="" Type="10" Text1="" Text2="" Text3="" />
			<Param Out="" Type="1" Text1="Lead Sound Designer" Text2="" Text3="" />
			<Param Out="" Type="2" Text1="" Text2="Daichi Aoki" Text3="" />
			<Param Out="" Type="10" Text1="" Text2="" Text3="" />
			<Param Out="" Type="1" Text1="Sound Designer" Text2="" Text3="" />
			<Param Out="" Type="3" Text1="" Text2="Daichi Ishihara" Text3="" />
			<Param Out="" Type="3" Text1="" Text2="Joya Shioiri" Text3="" />
			<Param Out="" Type="10" Text1="" Text2="" Text3="" />
			<Param Out="" Type="1" Text1="Planning Support" Text2="" Text3="" />
			<Param Out="" Type="3" Text1="" Text2="Osamu Yamauchi" Text3="" />
			<Param Out="" Type="3" Text1="" Text2="Daisuke Nakajima" Text3="" />
			<Param Out="" Type="3" Text1="" Text2="Kana Ishikawa" Text3="" />
			<Param Out="" Type="3" Text1="" Text2="Hina Ito" Text3="" />
			<Param Out="" Type="10" Text1="" Text2="" Text3="" />
			<Param Out="" Type="1" Text1="Coordinator" Text2="" Text3="" />
			<Param Out="" Type="3" Text1="" Text2="Kenji Yamada" Text3="" />
			<Param Out="" Type="3" Text1="" Text2="Yuji Mitani" Text3="" />
			<Param Out="" Type="12" Text1="" Text2="" Text3="" />
			<Param Out="" Type="1" Text1="Voice Cast" Text2="" Text3="" />
			<Param Out="" Type="5" Text1="Lueur (Male)" Text2="Hiro Shimono" Text3="" />
			<Param Out="" Type="5" Text1="Lueur (Female)" Text2="Aya Endo" Text3="" />
			<Param Out="" Type="5" Text1="Vandre" Text2="Youji Ueda" Text3="" />
			<Param Out="" Type="5" Text1="Clan" Text2="Kohei Amasaki" Text3="" />
			<Param Out="" Type="5" Text1="Fram" Text2="Sayaka Sembongi" Text3="" />
			<Param Out="" Type="5" Text1="Alfred" Text2="Ryohei Kimura" Text3="" />
			<Param Out="" Type="5" Text1="Boucheron" Text2="Toru Sakurai" Text3="" />
			<Param Out="" Type="5" Text1="Etie" Text2="Tomomi Mineuchi" Text3="" />
			<Param Out="" Type="5" Text1="Celine" Text2="Akari Kito" Text3="" />
			<Param Out="" Type="5" Text1="Louis" Text2="Haruki Ishiya" Text3="" />
			<Param Out="" Type="5" Text1="Chloe" Text2="Saori Hayami" Text3="" />
			<Param Out="" Type="5" Text1="Diamand" Text2="Junichi Suwabe" Text3="" />
			<Param Out="" Type="5" Text1="Amber" Text2="Atsushi Tamaru" Text3="" />
			<Param Out="" Type="5" Text1="Jade" Text2="Marie Miyake" Text3="" />
			<Param Out="" Type="5" Text1="Staluke" Text2="Nobuhiko Okamoto" Text3="" />
			<Param Out="" Type="5" Text1="Lapis" Text2="Tomoyo Takayanagi" Text3="" />
			<Param Out="" Type="5" Text1="Citrinica" Text2="Ikumi Hasegawa" Text3="" />
			<Param Out="" Type="5" Text1="Ivy" Text2="Yoko Hikasa" Text3="" />
			<Param Out="" Type="5" Text1="Zelkova" Text2="Yu Taniguchi" Text3="" />
			<Param Out="" Type="5" Text1="Kagetsu" Text2="Takehito Koyasu" Text3="" />
			<Param Out="" Type="5" Text1="Hortensia" Text2="Hina Kino" Text3="" />
			<Param Out="" Type="5" Text1="Rosado" Text2="Shouta Aoi" Text3="" />
			<Param Out="" Type="5" Text1="Goldmary" Text2="Natsumi Takamori" Text3="" />
			<Param Out="" Type="5" Text1="Misutira" Text2="Ami Koshimizu" Text3="" />
			<Param Out="" Type="5" Text1="Merin" Text2="Nanako Mori" Text3="" />
			<Param Out="" Type="5" Text1="Panetone" Text2="Yukina Shuto" Text3="" />
			<Param Out="" Type="5" Text1="Fogato" Text2="KENN" Text3="" />
			<Param Out="" Type="5" Text1="Pandoro" Text2="Genki Okawa" Text3="" />
			<Param Out="" Type="5" Text1="Bonet" Text2="Tomohiro Ono" Text3="" />
			<Param Out="" Type="5" Text1="Anna" Text2="Saori Seto" Text3="" />
			<Param Out="" Type="5" Text1="Jean" Text2="Risae Matsuda" Text3="" />
			<Param Out="" Type="5" Text1="Yunaka" Text2="Fairouz Ai" Text3="" />
			<Param Out="" Type="5" Text1="Seadas" Text2="Shogo Sakamoto" Text3="" />
			<Param Out="" Type="5" Text1="Linden" Text2="Takehiro Hasu" Text3="" />
			<Param Out="" Type="5" Text1="Saphir" Text2="Sachiko Okada" Text3="" />
			<Param Out="" Type="5" Text1="Veyre" Text2="Reina Ueda" Text3="" />
			<Param Out="" Type="5" Text1="Mauve" Text2="Tomoaki Maeno" Text3="" />
			<Param Out="" Type="5" Text1="Sepia" Text2="Rica Fukami" Text3="" />
			<Param Out="" Type="5" Text1="Gris" Text2="Kenjiro Tsuda" Text3="" />
			<Param Out="" Type="5" Text1="Marron" Text2="Ruriko Aoki" Text3="" />
			<Param Out="" Type="5" Text1="Eve" Text2="Kyoko Hikami" Text3="" />
			<Param Out="" Type="5" Text1="Morion" Text2="Kento Fujinuma" Text3="" />
			<Param Out="" Type="5" Text1="Hyacinth" Text2="Takashi Nagasako" Text3="" />
			<Param Out="" Type="5" Text1="Sfoglia" Text2="Mika Kanda" Text3="" />
			<Param Out="" Type="5" Text1="Lumiere" Text2="Kotono Mitsuishi" Text3="" />
			<Param Out="" Type="5" Text1="Sombre" Text2="Katsuyuki Konishi" Text3="" />
			<Param Out="" Type="10" Text1="" Text2="" Text3="" />
			<Param Out="" Type="5" Text1="Marth" Text2="Hikaru Midorikawa" Text3="" />
			<Param Out="" Type="5" Text1="Celica" Text2="Nao Toyama" Text3="" />
			<Param Out="" Type="5" Text1="Siglud/Sigurd" Text2="Toshiyuki Morikawa" Text3="" />
			<Param Out="" Type="5" Text1="Leaf/Leif" Text2="Kenichi Suzumura" Text3="" />
			<Param Out="" Type="5" Text1="Roy" Text2="Jun Fukuyama" Text3="" />
			<Param Out="" Type="5" Text1="Lin/Lyn" Text2="Makiko Ohmoto" Text3="" />
			<Param Out="" Type="5" Text1="Eirik/Eirika" Text2="Kaori Mizuhashi" Text3="" />
			<Param Out="" Type="5" Text1="Ephraim" Text2="Taku Yashiro" Text3="" />
			<Param Out="" Type="5" Text1="Ike" Text2="Michihiko Hagi" Text3="" />
			<Param Out="" Type="5" Text1="Micaiah" Text2="Natsuko Kuwatani" Text3="" />
			<Param Out="" Type="5" Text1="Lucina" Text2="Yu Kobayashi" Text3="" />
			<Param Out="" Type="5" Text1="Kamui/Corrin" Text2="Satomi Sato" Text3="" />
			<Param Out="" Type="5" Text1="Byleth" Text2="Yusuke Kobayashi" Text3="" />
			<Param Out="" Type="10" Text1="" Text2="" Text3="" />
			<Param Out="" Type="5" Text1="Derton" Text2="Yuu Maeda" Text3="" />
			<Param Out="" Type="5" Text1="Agnishu" Text2="Nozomi Shirota" Text3="" />
			<Param Out="" Type="5" Text1="Pine" Text2="Koki Koyasu" Text3="" />
			<Param Out="" Type="5" Text1="Karnei" Text2="Asuka Goda" Text3="" />
			<Param Out="" Type="5" Text1="Anju" Text2="Mika Kanda" Text3="" />
			<Param Out="" Type="5" Text1="Sean" Text2="Masaaki Yano" Text3="" />
			<Param Out="" Type="5" Text1="Abium" Text2="Marie Miyake" Text3="" />
			<Param Out="" Type="5" Text1="Rhodan" Text2="Masaaki Yano" Text3="" />
			<Param Out="" Type="5" Text1="Nelke" Text2="Yuu Maeda" Text3="" />
			<Param Out="" Type="5" Text1="Teranda" Text2="Takehiro Hasu" Text3="" />
			<Param Out="" Type="5" Text1="Tettsy" Text2="Kento Fujinuma" Text3="" />
			<Param Out="" Type="5" Text1="Tottwi" Text2="Masaaki Yano" Text3="" />
			<Param Out="" Type="5" Text1="Mitan" Text2="Ikumi Hasegawa" Text3="" />
			<Param Out="" Type="11" Text1="" Text2="" Text3="" />
			<Param Out="" Type="1" Text1="English Voice Cast" Text2="" Text3="" />
			<Param Out="" Type="5" Text1="Alear (Male)" Text2="Brandon McInnis" Text3="" />
			<Param Out="" Type="5" Text1="Alear (Female)" Text2="Laura Stahl" Text3="" />
			<Param Out="" Type="5" Text1="Vander" Text2="Jason Vande Brake" Text3="" />
			<Param Out="" Type="5" Text1="Clanne" Text2="Justin Briner" Text3="" />
			<Param Out="" Type="5" Text1="Framme" Text2="Lisa Reimold" Text3="" />
			<Param Out="" Type="5" Text1="Alfred" Text2="Nick Wolfhard" Text3="" />
			<Param Out="" Type="5" Text1="Boucheron" Text2="Joe Hernandez" Text3="" />
			<Param Out="" Type="5" Text1="Etie" Text2="Trina Nishimura" Text3="" />
			<Param Out="" Type="5" Text1="Céline" Text2="Rachelle Heger" Text3="" />
			<Param Out="" Type="5" Text1="Louis" Text2="J. Michael Tatum" Text3="" />
			<Param Out="" Type="5" Text1="Chloé" Text2="Elizabeth Simmons" Text3="" />
			<Param Out="" Type="5" Text1="Diamant" Text2="Stephen Fu" Text3="" />
			<Param Out="" Type="5" Text1="Amber" Text2="Parker Way" Text3="" />
			<Param Out="" Type="5" Text1="Jade" Text2="Katelyn Gault" Text3="" />
			<Param Out="" Type="5" Text1="Alcryst" Text2="Micah Solusod" Text3="" />
			<Param Out="" Type="5" Text1="Lapis" Text2="Kimberly Woods" Text3="" />
			<Param Out="" Type="5" Text1="Citrinne" Text2="Britney Karbowski" Text3="" />
			<Param Out="" Type="5" Text1="Ivy" Text2="Reba Buhr" Text3="" />
			<Param Out="" Type="5" Text1="Zelkov" Text2="David Matranga" Text3="" />
			<Param Out="" Type="5" Text1="Kagetsu" Text2="Khoi Dao" Text3="" />
			<Param Out="" Type="5" Text1="Hortensia" Text2="Amber Connor" Text3="" />
			<Param Out="" Type="5" Text1="Rosado" Text2="Brian Timothy Anderson" Text3="" />
			<Param Out="" Type="5" Text1="Goldmary" Text2="Maureen Price" Text3="" />
			<Param Out="" Type="5" Text1="Timerra" Text2="Dani Chambers" Text3="" />
			<Param Out="" Type="5" Text1="Merrin" Text2="Cristina &quot;Vee&quot; Valenzuela" Text3="" />
			<Param Out="" Type="5" Text1="Panette" Text2="Melissa Hutchison" Text3="" />
			<Param Out="" Type="5" Text1="Fogado" Text2="Zeno Robinson" Text3="" />
			<Param Out="" Type="5" Text1="Pandreo" Text2="Ricco Fajardo" Text3="" />
			<Param Out="" Type="5" Text1="Bunet" Text2="Ian Sinclair" Text3="" />
			<Param Out="" Type="5" Text1="Anna" Text2="Monica Rial" Text3="" />
			<Param Out="" Type="5" Text1="Jean" Text2="Colleen O'Shaughnessey" Text3="" />
			<Param Out="" Type="5" Text1="Yunaka" Text2="Laura Post" Text3="" />
			<Param Out="" Type="5" Text1="Seadall" Text2="Griffin Puatu" Text3="" />
			<Param Out="" Type="5" Text1="Lindon" Text2="James Wade" Text3="" />
			<Param Out="" Type="5" Text1="Saphir" Text2="Cassie Ewulu" Text3="" />
			<Param Out="" Type="5" Text1="Veyle" Text2="Megan Taylor Harvey" Text3="" />
			<Param Out="" Type="5" Text1="Mauvier" Text2="Gavin Hammon" Text3="" />
			<Param Out="" Type="5" Text1="Zephia" Text2="Elizabeth Maxwell" Text3="" />
			<Param Out="" Type="5" Text1="Griss" Text2="Jamison Boaz" Text3="" />
			<Param Out="" Type="5" Text1="Marni" Text2="Sarah Williams" Text3="" />
			<Param Out="" Type="5" Text1="Ève" Text2="Megan Hollingshead" Text3="" />
			<Param Out="" Type="5" Text1="Morion" Text2="Josh Petersdorf" Text3="" />
			<Param Out="" Type="5" Text1="Hyacinth" Text2="Brook Chalmers" Text3="" />
			<Param Out="" Type="5" Text1="Seforia" Text2="Afi Ekulona" Text3="" />
			<Param Out="" Type="5" Text1="Lumera" Text2="Julia McIlvaine" Text3="" />
			<Param Out="" Type="5" Text1="Sombron" Text2="Erik Braa" Text3="" />
			<Param Out="" Type="10" Text1="" Text2="" Text3="" />
			<Param Out="" Type="5" Text1="Marth" Text2="Yuri Lowenthal" Text3="" />
			<Param Out="" Type="5" Text1="Celica" Text2="Erica Lindbeck" Text3="" />
			<Param Out="" Type="5" Text1="Sigurd" Text2="Grant George" Text3="" />
			<Param Out="" Type="5" Text1="Leif" Text2="Nicolas Roye" Text3="" />
			<Param Out="" Type="5" Text1="Roy" Text2="Ray Chase" Text3="" />
			<Param Out="" Type="5" Text1="Lyn" Text2="Wendee Lee" Text3="" />
			<Param Out="" Type="5" Text1="Eirika" Text2="Kira Buckland" Text3="" />
			<Param Out="" Type="5" Text1="Ike/Ephraim" Text2="Greg Chun" Text3="" />
			<Param Out="" Type="5" Text1="Micaiah" Text2="Veronica Taylor" Text3="" />
			<Param Out="" Type="5" Text1="Lucina" Text2="Alexis Tipton" Text3="" />
			<Param Out="" Type="5" Text1="Corrin" Text2="Marcella Lentz-Pope" Text3="" />
			<Param Out="" Type="5" Text1="Byleth" Text2="Zach Aguilar" Text3="" />
			<Param Out="" Type="10" Text1="" Text2="" Text3="" />
			<Param Out="" Type="1" Text1="Additional Voices" Text2="" Text3="" />
			<Param Out="" Type="4" Text1="" Text2="Jonah Scott" Text3="" />
			<Param Out="" Type="4" Text1="" Text2="Patrick Seitz" Text3="" />
			<Param Out="" Type="4" Text1="" Text2="Danni Hunt" Text3="" />
			<Param Out="" Type="4" Text1="" Text2="Frank Todaro" Text3="" />
			<Param Out="" Type="4" Text1="" Text2="Heather Gonzalez" Text3="" />
			<Param Out="" Type="4" Text1="" Text2="Caitlyn Elizabeth" Text3="" />
			<Param Out="" Type="12" Text1="" Text2="" Text3="" />
			<Param Out="" Type="1" Text1="Sound Supervisor" Text2="" Text3="" />
			<Param Out="" Type="2" Text1="" Text2="Yuka Tsujiyoko" Text3="" />
			<Param Out="" Type="10" Text1="" Text2="" Text3="" />
			<Param Out="" Type="1" Text1="Composer &amp; Mastering Engineer" Text2="" Text3="" />
			<Param Out="" Type="2" Text1="" Text2="Fumihiro Isobe" Text3="" />
			<Param Out="" Type="12" Text1="" Text2="" Text3="" />
			<Param Out="" Type="8" Text1="Dimension Cruise" Text2="" Text3="" />
			<Param Out="" Type="1" Text1="Composer &amp; Recording Engineer" Text2="" Text3="" />
			<Param Out="" Type="2" Text1="" Text2="Takafumi Wada" Text3="" />
			<Param Out="" Type="10" Text1="" Text2="" Text3="" />
			<Param Out="" Type="1" Text1="Arranger &amp; Pro Tools Operator" Text2="" Text3="" />
			<Param Out="" Type="2" Text1="" Text2="Ryosuke Kawasaki" Text3="" />
			<Param Out="" Type="10" Text1="" Text2="" Text3="" />
			<Param Out="" Type="1" Text1="Arranger" Text2="" Text3="" />
			<Param Out="" Type="2" Text1="" Text2="Sumika Horiguchi" Text3="" />
			<Param Out="" Type="10" Text1="" Text2="" Text3="" />
			<Param Out="" Type="1" Text1="Recorded at Dimension Cruise Studio" Text2="" Text3="" />
			<Param Out="" Type="12" Text1="" Text2="" Text3="" />
			<Param Out="" Type="8" Text1="Witchcraft" Text2="" Text3="" />
			<Param Out="" Type="1" Text1="Performer Coordinator" Text2="" Text3="" />
			<Param Out="" Type="2" Text1="" Text2="Yoji Sugiyama" Text3="" />
			<Param Out="" Type="10" Text1="" Text2="" Text3="" />
			<Param Out="" Type="1" Text1="Instrument Performer" Text2="" Text3="" />
			<Param Out="" Type="1" Text1="Flute, Piccolo,  Alto Flute, Ethnic Flutes, Recorder" Text2="" Text3="" />
			<Param Out="" Type="2" Text1="" Text2="Hideyo Takakuwa" Text3="" />
			<Param Out="" Type="10" Text1="" Text2="" Text3="" />
			<Param Out="" Type="1" Text1="Clarinet, Bass Clarinet" Text2="" Text3="" />
			<Param Out="" Type="3" Text1="" Text2="Naka Hidehito" Text3="" />
			<Param Out="" Type="3" Text1="" Text2="Yamane Kimio" Text3="" />
			<Param Out="" Type="10" Text1="" Text2="" Text3="" />
			<Param Out="" Type="1" Text1="Oboe, English Horn, Oboe d'Amore" Text2="" Text3="" />
			<Param Out="" Type="2" Text1="" Text2="Takayuki Mogami" Text3="" />
			<Param Out="" Type="10" Text1="" Text2="" Text3="" />
			<Param Out="" Type="1" Text1="Oboe, English Horn" Text2="" Text3="" />
			<Param Out="" Type="2" Text1="" Text2="Satoshi Shoji" Text3="" />
			<Param Out="" Type="10" Text1="" Text2="" Text3="" />
			<Param Out="" Type="1" Text1="Bassoon" Text2="" Text3="" />
			<Param Out="" Type="2" Text1="" Text2="Akira Ishikawa" Text3="" />
			<Param Out="" Type="10" Text1="" Text2="" Text3="" />
			<Param Out="" Type="1" Text1="Trumpet" Text2="" Text3="" />
			<Param Out="" Type="4" Text1="" Text2="Kenichi Tsujimoto" Text3="" />
			<Param Out="" Type="4" Text1="" Text2="Yoon Cheonho" Text3="" />
			<Param Out="" Type="4" Text1="" Text2="Shun Ito" Text3="" />
			<Param Out="" Type="10" Text1="" Text2="" Text3="" />
			<Param Out="" Type="1" Text1="Trombone, Bass Trombone" Text2="" Text3="" />
			<Param Out="" Type="2" Text1="" Text2="Hikaru Koga" Text3="" />
			<Param Out="" Type="10" Text1="" Text2="" Text3="" />
			<Param Out="" Type="1" Text1="E. Guitar, A. Guitar" Text2="" Text3="" />
			<Param Out="" Type="3" Text1="" Text2="Fumihiro Isobe" Text3="" />
			<Param Out="" Type="3" Text1="" Text2="Harutoshi Ito" Text3="" />
			<Param Out="" Type="10" Text1="" Text2="" Text3="" />
			<Param Out="" Type="1" Text1="E. Bass" Text2="" Text3="" />
			<Param Out="" Type="2" Text1="" Text2="Toshino Tanabe" Text3="" />
			<Param Out="" Type="10" Text1="" Text2="" Text3="" />
			<Param Out="" Type="1" Text1="Harp" Text2="" Text3="" />
			<Param Out="" Type="2" Text1="" Text2="Tomoyuki Asakawa" Text3="" />
			<Param Out="" Type="10" Text1="" Text2="" Text3="" />
			<Param Out="" Type="1" Text1="Soprano" Text2="" Text3="" />
			<Param Out="" Type="2" Text1="" Text2="Chika Higashinaka (The Philharmonic Chorus of Tokyo)" Text3="" />
			<Param Out="" Type="10" Text1="" Text2="" Text3="" />
			<Param Out="" Type="1" Text1="Tenor" Text2="" Text3="" />
			<Param Out="" Type="2" Text1="" Text2="Kazushige Shimura (The Philharmonic Chorus of Tokyo)" Text3="" />
			<Param Out="" Type="10" Text1="" Text2="" Text3="" />
			<Param Out="" Type="1" Text1="Violin" Text2="" Text3="" />
			<Param Out="" Type="4" Text1="" Text2="Koichiro Muroya" Text3="" />
			<Param Out="" Type="4" Text1="" Text2="Hanako Uesato" Text3="" />
			<Param Out="" Type="4" Text1="" Text2="Shoko Oki " Text3="" />
			<Param Out="" Type="4" Text1="" Text2="Yuya Yanagihara" Text3="" />
			<Param Out="" Type="4" Text1="" Text2="Rina Odera" Text3="" />
			<Param Out="" Type="10" Text1="" Text2="" Text3="" />
			<Param Out="" Type="1" Text1="Viola" Text2="" Text3="" />
			<Param Out="" Type="3" Text1="" Text2="Kintaro Hagiya" Text3="" />
			<Param Out="" Type="3" Text1="" Text2="Shoko Mabuchi" Text3="" />
			<Param Out="" Type="10" Text1="" Text2="" Text3="" />
			<Param Out="" Type="1" Text1="Cello" Text2="" Text3="" />
			<Param Out="" Type="2" Text1="" Text2="Yuki Mizuno" Text3="" />
			<Param Out="" Type="10" Text1="" Text2="" Text3="" />
			<Param Out="" Type="1" Text1="Contrabass" Text2="" Text3="" />
			<Param Out="" Type="2" Text1="" Text2="Koji Akaike" Text3="" />
			<Param Out="" Type="12" Text1="" Text2="" Text3="" />
			<Param Out="" Type="8" Text1="TWOFIVE. Staff" Text2="" Text3="" />
			<Param Out="" Type="1" Text1="Voice Recording &amp; Editing" Text2="" Text3="" />
			<Param Out="" Type="1" Text1="Casting Support" Text2="" Text3="" />
			<Param Out="" Type="2" Text1="" Text2="Bungo Fujiwara (TWOFIVE)" Text3="" />
			<Param Out="" Type="10" Text1="" Text2="" Text3="" />
			<Param Out="" Type="1" Text1="Recording Director" Text2="" Text3="" />
			<Param Out="" Type="2" Text1="" Text2="Hitomi Matsuki (TWOFIVE)" Text3="" />
			<Param Out="" Type="10" Text1="" Text2="" Text3="" />
			<Param Out="" Type="1" Text1="Assistant Director" Text2="" Text3="" />
			<Param Out="" Type="2" Text1="" Text2="Eri Sakurai (TWOFIVE)" Text3="" />
			<Param Out="" Type="10" Text1="" Text2="" Text3="" />
			<Param Out="" Type="1" Text1="Recording Engineer" Text2="" Text3="" />
			<Param Out="" Type="3" Text1="" Text2="Ayaka Tominaga (TWOFIVE)" Text3="" />
			<Param Out="" Type="3" Text1="" Text2="Kaito Mochizuki (TWOFIVE)" Text3="" />
			<Param Out="" Type="3" Text1="" Text2="Masayoshi Ota (TWOFIVE)" Text3="" />
			<Param Out="" Type="10" Text1="" Text2="" Text3="" />
			<Param Out="" Type="1" Text1="Voice Editor" Text2="" Text3="" />
			<Param Out="" Type="3" Text1="" Text2="Junpei Ikawa (TWOFIVE)" Text3="" />
			<Param Out="" Type="3" Text1="" Text2="Takashi Shinbori" Text3="" />
			<Param Out="" Type="3" Text1="" Text2="Yoshikazu Iida (MUTS music studio)" Text3="" />
			<Param Out="" Type="3" Text1="" Text2="Ryoji Takahashi (AZcreative)" Text3="" />
			<Param Out="" Type="3" Text1="" Text2="Hiroshi Kojima (AZcreative)" Text3="" />
			<Param Out="" Type="3" Text1="" Text2="Himeka Matsuyama (AZcreative)" Text3="" />
			<Param Out="" Type="10" Text1="" Text2="" Text3="" />
			<Param Out="" Type="1" Text1="Sound Design (MA)" Text2="" Text3="" />
			<Param Out="" Type="1" Text1="Sound Designer" Text2="" Text3="" />
			<Param Out="" Type="3" Text1="" Text2="Junpei Ikawa (TWOFIVE)" Text3="" />
			<Param Out="" Type="3" Text1="" Text2="Kosei Muraki (TWOFIVE)" Text3="" />
			<Param Out="" Type="12" Text1="" Text2="" Text3="" />
			<Param Out="" Type="8" Text1="Synthese Co., Ltd." Text2="" Text3="" />
			<Param Out="" Type="1" Text1="Scenario Writer" Text2="" Text3="" />
			<Param Out="" Type="3" Text1="" Text2="Yukinori Kitajima" Text3="" />
			<Param Out="" Type="3" Text1="" Text2="Hiroshi Takane" Text3="" />
			<Param Out="" Type="3" Text1="" Text2="Takayoshi Muto" Text3="" />
			<Param Out="" Type="3" Text1="" Text2="Tatsuro Hamano" Text3="" />
			<Param Out="" Type="12" Text1="" Text2="" Text3="" />
			<Param Out="" Type="8" Text1="Crico,Inc." Text2="" Text3="" />
			<Param Out="" Type="1" Text1="Scenario Writer" Text2="" Text3="" />
			<Param Out="" Type="4" Text1="" Text2="Masaya Ikemura" Text3="" />
			<Param Out="" Type="4" Text1="" Text2="Eiichi Konomura" Text3="" />
			<Param Out="" Type="4" Text1="" Text2="Ako Tsubaki" Text3="" />
			<Param Out="" Type="4" Text1="" Text2="Kei Seta" Text3="" />
			<Param Out="" Type="4" Text1="" Text2="Utonapi" Text3="" />
			<Param Out="" Type="10" Text1="" Text2="" Text3="" />
			<Param Out="" Type="1" Text1="Planner" Text2="" Text3="" />
			<Param Out="" Type="2" Text1="" Text2="Keisuke Mizuno" Text3="" />
			<Param Out="" Type="12" Text1="" Text2="" Text3="" />
			<Param Out="" Type="8" Text1="Himawari Studio Co.,Ltd" Text2="" Text3="" />
			<Param Out="" Type="1" Text1="Producer" Text2="" Text3="" />
			<Param Out="" Type="2" Text1="" Text2="Yoshitaka Tanigawa" Text3="" />
			<Param Out="" Type="10" Text1="" Text2="" Text3="" />
			<Param Out="" Type="1" Text1="Designer &amp; Event Illustration" Text2="" Text3="" />
			<Param Out="" Type="2" Text1="" Text2="Gen Yamazaki" Text3="" />
			<Param Out="" Type="12" Text1="" Text2="" Text3="" />
			<Param Out="" Type="8" Text1="HAUTECOUTURE INC.Ltd" Text2="" Text3="" />
			<Param Out="" Type="1" Text1="Director" Text2="" Text3="" />
			<Param Out="" Type="4" Text1="" Text2="Kouta Kanno" Text3="" />
			<Param Out="" Type="4" Text1="" Text2="Masaya Yasuno" Text3="" />
			<Param Out="" Type="4" Text1="" Text2="Satoshi Nakata" Text3="" />
			<Param Out="" Type="4" Text1="" Text2="Shinya Nakamura" Text3="" />
			<Param Out="" Type="4" Text1="" Text2="Teppei Kajiyama" Text3="" />
			<Param Out="" Type="10" Text1="" Text2="" Text3="" />
			<Param Out="" Type="1" Text1="Designer" Text2="" Text3="" />
			<Param Out="" Type="4" Text1="" Text2="Aika Watanabe" Text3="" />
			<Param Out="" Type="4" Text1="" Text2="Akihiro Nagae" Text3="" />
			<Param Out="" Type="4" Text1="" Text2="Ayana Kita" Text3="" />
			<Param Out="" Type="4" Text1="" Text2="Ayane Ebina" Text3="" />
			<Param Out="" Type="4" Text1="" Text2="Ayuu Nishio" Text3="" />
			<Param Out="" Type="4" Text1="" Text2="Chieri Torigoe" Text3="" />
			<Param Out="" Type="4" Text1="" Text2="Chihiro Tsutsui" Text3="" />
			<Param Out="" Type="4" Text1="" Text2="Emi Watanabe" Text3="" />
			<Param Out="" Type="4" Text1="" Text2="Fumika Suzuki" Text3="" />
			<Param Out="" Type="4" Text1="" Text2="Futami Takahashi" Text3="" />
			<Param Out="" Type="4" Text1="" Text2="Hayate Ikeno" Text3="" />
			<Param Out="" Type="4" Text1="" Text2="Hikaru Hara" Text3="" />
			<Param Out="" Type="4" Text1="" Text2="Hinako Amanai" Text3="" />
			<Param Out="" Type="4" Text1="" Text2="Ikumi Motoda" Text3="" />
			<Param Out="" Type="4" Text1="" Text2="Izumi Takabayashi" Text3="" />
			<Param Out="" Type="4" Text1="" Text2="Jun Shigematsu" Text3="" />
			<Param Out="" Type="4" Text1="" Text2="Kenta Karuki" Text3="" />
			<Param Out="" Type="4" Text1="" Text2="Kie Nagaoka" Text3="" />
			<Param Out="" Type="4" Text1="" Text2="Mikiko Toyoda" Text3="" />
			<Param Out="" Type="4" Text1="" Text2="Momoko Kawakami" Text3="" />
			<Param Out="" Type="4" Text1="" Text2="Nanami Shoji" Text3="" />
			<Param Out="" Type="4" Text1="" Text2="Nao Omatsu" Text3="" />
			<Param Out="" Type="4" Text1="" Text2="Natsumi Kuromaru" Text3="" />
			<Param Out="" Type="4" Text1="" Text2="Natsumi Nishiuchi" Text3="" />
			<Param Out="" Type="4" Text1="" Text2="Runa Saito" Text3="" />
			<Param Out="" Type="4" Text1="" Text2="Ryo Nakanishi" Text3="" />
			<Param Out="" Type="4" Text1="" Text2="Sayaka Takemoto" Text3="" />
			<Param Out="" Type="4" Text1="" Text2="Seiko Morimoto" Text3="" />
			<Param Out="" Type="4" Text1="" Text2="Taiki Kuwahara" Text3="" />
			<Param Out="" Type="4" Text1="" Text2="Yoshihito Ishiguro" Text3="" />
			<Param Out="" Type="4" Text1="" Text2="Yuka  Hoshina" Text3="" />
			<Param Out="" Type="4" Text1="" Text2="Yukina Ikehara" Text3="" />
			<Param Out="" Type="4" Text1="" Text2="Yutaka Wada" Text3="" />
			<Param Out="" Type="12" Text1="" Text2="" Text3="" />
			<Param Out="" Type="8" Text1="ChronoJuvenile Inc." Text2="" Text3="" />
			<Param Out="" Type="1" Text1="Director" Text2="" Text3="" />
			<Param Out="" Type="3" Text1="" Text2="Junichiro Kuramoto" Text3="" />
			<Param Out="" Type="3" Text1="" Text2="Yuri Sato" Text3="" />
			<Param Out="" Type="10" Text1="" Text2="" Text3="" />
			<Param Out="" Type="1" Text1="Planner" Text2="" Text3="" />
			<Param Out="" Type="3" Text1="" Text2="Shizuka Hashimoto" Text3="" />
			<Param Out="" Type="3" Text1="" Text2="Wataru Nishimoto" Text3="" />
			<Param Out="" Type="12" Text1="" Text2="" Text3="" />
			<Param Out="" Type="8" Text1="Digital Media Lab., Inc." Text2="" Text3="" />
			<Param Out="" Type="1" Text1="Manager" Text2="" Text3="" />
			<Param Out="" Type="2" Text1="" Text2="Shunsuke Kamada" Text3="" />
			<Param Out="" Type="10" Text1="" Text2="" Text3="" />
			<Param Out="" Type="1" Text1="Production Coordinator" Text2="" Text3="" />
			<Param Out="" Type="4" Text1="" Text2="Michiyo Hamada" Text3="" />
			<Param Out="" Type="4" Text1="" Text2="Haruo Imaizumi" Text3="" />
			<Param Out="" Type="4" Text1="" Text2="Ikumi Teramoto" Text3="" />
			<Param Out="" Type="10" Text1="" Text2="" Text3="" />
			<Param Out="" Type="1" Text1="3D Designer" Text2="" Text3="" />
			<Param Out="" Type="4" Text1="" Text2="Tadashi Tamura" Text3="" />
			<Param Out="" Type="4" Text1="" Text2=" Yuuki Kokura" Text3="" />
			<Param Out="" Type="4" Text1="" Text2="Yuki Higashiguchi" Text3="" />
			<Param Out="" Type="4" Text1="" Text2="Aya Kamei" Text3="" />
			<Param Out="" Type="4" Text1="" Text2="Hajime Saitou" Text3="" />
			<Param Out="" Type="10" Text1="" Text2="" Text3="" />
			<Param Out="" Type="1" Text1="Motion Actor" Text2="" Text3="" />
			<Param Out="" Type="4" Text1="" Text2="Hironobu Hagihara" Text3="" />
			<Param Out="" Type="4" Text1="" Text2="Yumi Horie" Text3="" />
			<Param Out="" Type="4" Text1="" Text2="Ryo Heitaku" Text3="" />
			<Param Out="" Type="12" Text1="" Text2="" Text3="" />
			<Param Out="" Type="8" Text1="ACCESS GAMES INC." Text2="" Text3="" />
			<Param Out="" Type="1" Text1="Producer" Text2="" Text3="" />
			<Param Out="" Type="2" Text1="" Text2="Nobuo Tomita" Text3="" />
			<Param Out="" Type="10" Text1="" Text2="" Text3="" />
			<Param Out="" Type="1" Text1="Manager" Text2="" Text3="" />
			<Param Out="" Type="2" Text1="" Text2="Hitoshi Okamoto" Text3="" />
			<Param Out="" Type="10" Text1="" Text2="" Text3="" />
			<Param Out="" Type="1" Text1="Assistant Manager" Text2="" Text3="" />
			<Param Out="" Type="2" Text1="" Text2="Kazunori Kakiuchi" Text3="" />
			<Param Out="" Type="10" Text1="" Text2="" Text3="" />
			<Param Out="" Type="1" Text1="Costume Designer" Text2="" Text3="" />
			<Param Out="" Type="2" Text1="" Text2="Natsumi Nishiyama" Text3="" />
			<Param Out="" Type="10" Text1="" Text2="" Text3="" />
			<Param Out="" Type="1" Text1="3D Designer" Text2="" Text3="" />
			<Param Out="" Type="3" Text1="" Text2="Akihiko Eguchi" Text3="" />
			<Param Out="" Type="3" Text1="" Text2="Hiroshi Imaoka" Text3="" />
			<Param Out="" Type="12" Text1="" Text2="" Text3="" />
			<Param Out="" Type="8" Text1="OctHands Create" Text2="" Text3="" />
			<Param Out="" Type="1" Text1="3D Designer" Text2="" Text3="" />
			<Param Out="" Type="2" Text1="" Text2="Kentaro Yamamoto" Text3="" />
			<Param Out="" Type="12" Text1="" Text2="" Text3="" />
			<Param Out="" Type="8" Text1="D.A.G" Text2="" Text3="" />
			<Param Out="" Type="1" Text1="Producer" Text2="" Text3="" />
			<Param Out="" Type="2" Text1="" Text2="Eiki Takizawa" Text3="" />
			<Param Out="" Type="10" Text1="" Text2="" Text3="" />
			<Param Out="" Type="1" Text1="Art Director" Text2="" Text3="" />
			<Param Out="" Type="2" Text1="" Text2="Taichi Matsunaga" Text3="" />
			<Param Out="" Type="10" Text1="" Text2="" Text3="" />
			<Param Out="" Type="1" Text1="3DCG Director" Text2="" Text3="" />
			<Param Out="" Type="4" Text1="" Text2="Fumie Ikezoe" Text3="" />
			<Param Out="" Type="4" Text1="" Text2="Shohei Fukui" Text3="" />
			<Param Out="" Type="4" Text1="" Text2="Yuki Kurosu" Text3="" />
			<Param Out="" Type="10" Text1="" Text2="" Text3="" />
			<Param Out="" Type="1" Text1="Animation Director" Text2="" Text3="" />
			<Param Out="" Type="2" Text1="" Text2="Takashi Kogure" Text3="" />
			<Param Out="" Type="10" Text1="" Text2="" Text3="" />
			<Param Out="" Type="1" Text1="Lead Digital Artist" Text2="" Text3="" />
			<Param Out="" Type="3" Text1="" Text2="Kazuaki Iwata" Text3="" />
			<Param Out="" Type="3" Text1="" Text2="Seiichi Matsukawa" Text3="" />
			<Param Out="" Type="3" Text1="" Text2="Kei Masumura" Text3="" />
			<Param Out="" Type="3" Text1="" Text2="Inok Chun" Text3="" />
			<Param Out="" Type="10" Text1="" Text2="" Text3="" />
			<Param Out="" Type="1" Text1="Digital Artist" Text2="" Text3="" />
			<Param Out="" Type="4" Text1="" Text2="Yuki Koga" Text3="" />
			<Param Out="" Type="4" Text1="" Text2="Takashi Masunaga " Text3="" />
			<Param Out="" Type="4" Text1="" Text2="Shunpei Sakaguchi" Text3="" />
			<Param Out="" Type="4" Text1="" Text2="Zhou Wu" Text3="" />
			<Param Out="" Type="4" Text1="" Text2="Long Yin" Text3="" />
			<Param Out="" Type="4" Text1="" Text2="Naoya Iwashita" Text3="" />
			<Param Out="" Type="4" Text1="" Text2="Jun Tomoike" Text3="" />
			<Param Out="" Type="4" Text1="" Text2="Huang Yinwen" Text3="" />
			<Param Out="" Type="4" Text1="" Text2="Akira Matsushita" Text3="" />
			<Param Out="" Type="4" Text1="" Text2="Natsuho Hashimoto" Text3="" />
			<Param Out="" Type="4" Text1="" Text2="Hiroki Ohno" Text3="" />
			<Param Out="" Type="4" Text1="" Text2="Erina Koshi" Text3="" />
			<Param Out="" Type="4" Text1="" Text2="Satoshi Hanada" Text3="" />
			<Param Out="" Type="4" Text1="" Text2="Yoshihiro Sone" Text3="" />
			<Param Out="" Type="4" Text1="" Text2="Kenta Hikosaka" Text3="" />
			<Param Out="" Type="4" Text1="" Text2="Fuuma Kumasaki" Text3="" />
			<Param Out="" Type="10" Text1="" Text2="" Text3="" />
			<Param Out="" Type="1" Text1="Project Assistant" Text2="" Text3="" />
			<Param Out="" Type="3" Text1="" Text2="Takumi Namatame" Text3="" />
			<Param Out="" Type="3" Text1="" Text2="Kazushige Nakamura" Text3="" />
			<Param Out="" Type="10" Text1="" Text2="" Text3="" />
			<Param Out="" Type="1" Text1="Account Manager" Text2="" Text3="" />
			<Param Out="" Type="2" Text1="" Text2="Yusuke Shigeta" Text3="" />
			<Param Out="" Type="12" Text1="" Text2="" Text3="" />
			<Param Out="" Type="8" Text1="Mox Co.,Ltd" Text2="" Text3="" />
			<Param Out="" Type="1" Text1="Lead Animator" Text2="" Text3="" />
			<Param Out="" Type="2" Text1="" Text2="Takuya Deguchi" Text3="" />
			<Param Out="" Type="10" Text1="" Text2="" Text3="" />
			<Param Out="" Type="1" Text1="Animator" Text2="" Text3="" />
			<Param Out="" Type="2" Text1="" Text2="Kaito Chiba" Text3="" />
			<Param Out="" Type="10" Text1="" Text2="" Text3="" />
			<Param Out="" Type="1" Text1="Project Manager" Text2="" Text3="" />
			<Param Out="" Type="2" Text1="" Text2="Masaya Akiyama" Text3="" />
			<Param Out="" Type="10" Text1="" Text2="" Text3="" />
			<Param Out="" Type="1" Text1="Animator" Text2="" Text3="" />
			<Param Out="" Type="2" Text1="" Text2="Kenji Tachibana (MORIMORI)" Text3="" />
			<Param Out="" Type="12" Text1="" Text2="" Text3="" />
			<Param Out="" Type="8" Text1="Himawari Studio Co.,Ltd" Text2="" Text3="" />
			<Param Out="" Type="1" Text1="Producer" Text2="" Text3="" />
			<Param Out="" Type="2" Text1="" Text2="Yoshitaka Tanigawa" Text3="" />
			<Param Out="" Type="12" Text1="" Text2="" Text3="" />
			<Param Out="" Type="8" Text1="Graphinica,Inc. Kyoto Studio" Text2="" Text3="" />
			<Param Out="" Type="1" Text1="Technical Supervisor" Text2="" Text3="" />
			<Param Out="" Type="2" Text1="" Text2="Akihiro Komiya" Text3="" />
			<Param Out="" Type="10" Text1="" Text2="" Text3="" />
			<Param Out="" Type="1" Text1="Production Coordinator" Text2="" Text3="" />
			<Param Out="" Type="2" Text1="" Text2="Junichi Kawano" Text3="" />
			<Param Out="" Type="10" Text1="" Text2="" Text3="" />
			<Param Out="" Type="1" Text1="Lead Modeler" Text2="" Text3="" />
			<Param Out="" Type="2" Text1="" Text2="Shuhei Ishida" Text3="" />
			<Param Out="" Type="10" Text1="" Text2="" Text3="" />
			<Param Out="" Type="1" Text1="Modeler" Text2="" Text3="" />
			<Param Out="" Type="3" Text1="" Text2="Yuta Sekido" Text3="" />
			<Param Out="" Type="3" Text1="" Text2="Chen Yu Hao" Text3="" />
			<Param Out="" Type="12" Text1="" Text2="" Text3="" />
			<Param Out="" Type="8" Text1="Accord Seven Inc." Text2="" Text3="" />
			<Param Out="" Type="1" Text1="Modeler" Text2="" Text3="" />
			<Param Out="" Type="2" Text1="" Text2="Saori Matsumoto" Text3="" />
			<Param Out="" Type="12" Text1="" Text2="" Text3="" />
			<Param Out="" Type="8" Text1="DigisiteGraphics co.,Ltd" Text2="" Text3="" />
			<Param Out="" Type="1" Text1="Modeler" Text2="" Text3="" />
			<Param Out="" Type="3" Text1="" Text2="Hiroyuki Morita" Text3="" />
			<Param Out="" Type="3" Text1="" Text2="Akiho Aiba" Text3="" />
			<Param Out="" Type="12" Text1="" Text2="" Text3="" />
			<Param Out="" Type="8" Text1="aexinc.Ltd" Text2="" Text3="" />
			<Param Out="" Type="1" Text1="Lead Designer" Text2="" Text3="" />
			<Param Out="" Type="2" Text1="" Text2="Kenji Tsujimura" Text3="" />
			<Param Out="" Type="10" Text1="" Text2="" Text3="" />
			<Param Out="" Type="1" Text1="Designer" Text2="" Text3="" />
			<Param Out="" Type="3" Text1="" Text2="Tatsuro Goda" Text3="" />
			<Param Out="" Type="3" Text1="" Text2="Jyunichi Yokoyama" Text3="" />
			<Param Out="" Type="3" Text1="" Text2="Sagakova Alexandra" Text3="" />
			<Param Out="" Type="3" Text1="" Text2="Masaya Ozaki" Text3="" />
			<Param Out="" Type="10" Text1="" Text2="" Text3="" />
			<Param Out="" Type="1" Text1="Environment Art" Text2="" Text3="" />
			<Param Out="" Type="2" Text1="" Text2="Nobuo Umahara (RACOON CREATIVE)" Text3="" />
			<Param Out="" Type="10" Text1="" Text2="" Text3="" />
			<Param Out="" Type="1" Text1="VFX" Text2="" Text3="" />
			<Param Out="" Type="2" Text1="" Text2="Toru Abe" Text3="" />
			<Param Out="" Type="12" Text1="" Text2="" Text3="" />
			<Param Out="" Type="8" Text1="ANIMA. Staff" Text2="" Text3="" />
			<Param Out="" Type="1" Text1="Director" Text2="" Text3="" />
			<Param Out="" Type="2" Text1="" Text2="Hiroshi Chida" Text3="" />
			<Param Out="" Type="10" Text1="" Text2="" Text3="" />
			<Param Out="" Type="1" Text1="Storyboard" Text2="" Text3="" />
			<Param Out="" Type="2" Text1="" Text2="Hiroshi Chida" Text3="" />
			<Param Out="" Type="10" Text1="" Text2="" Text3="" />
			<Param Out="" Type="1" Text1="CG Director" Text2="" Text3="" />
			<Param Out="" Type="2" Text1="" Text2="Takeru Nakajima" Text3="" />
			<Param Out="" Type="10" Text1="" Text2="" Text3="" />
			<Param Out="" Type="1" Text1="Art Director" Text2="" Text3="" />
			<Param Out="" Type="2" Text1="" Text2="Yoshiyuki Okada" Text3="" />
			<Param Out="" Type="10" Text1="" Text2="" Text3="" />
			<Param Out="" Type="1" Text1="Assistant Art Director" Text2="" Text3="" />
			<Param Out="" Type="3" Text1="" Text2="Momoko Yamanaka" Text3="" />
			<Param Out="" Type="3" Text1="" Text2="Tsukasa Yunoue" Text3="" />
			<Param Out="" Type="10" Text1="" Text2="" Text3="" />
			<Param Out="" Type="1" Text1="Concept Art" Text2="" Text3="" />
			<Param Out="" Type="3" Text1="" Text2="Daisuke Yanagisawa" Text3="" />
			<Param Out="" Type="3" Text1="" Text2="Hiroaki Ueno" Text3="" />
			<Param Out="" Type="10" Text1="" Text2="" Text3="" />
			<Param Out="" Type="1" Text1="CG Supervisor" Text2="" Text3="" />
			<Param Out="" Type="2" Text1="" Text2="Kosuke Kama" Text3="" />
			<Param Out="" Type="10" Text1="" Text2="" Text3="" />
			<Param Out="" Type="1" Text1="Previs Artist" Text2="" Text3="" />
			<Param Out="" Type="2" Text1="" Text2="Makoto Seki" Text3="" />
			<Param Out="" Type="10" Text1="" Text2="" Text3="" />
			<Param Out="" Type="1" Text1="Character Modeling Supervisor" Text2="" Text3="" />
			<Param Out="" Type="2" Text1="" Text2="Masakazu Taira" Text3="" />
			<Param Out="" Type="10" Text1="" Text2="" Text3="" />
			<Param Out="" Type="1" Text1="Lead Character Modeling Artist" Text2="" Text3="" />
			<Param Out="" Type="2" Text1="" Text2="Ayame Okaizumi" Text3="" />
			<Param Out="" Type="10" Text1="" Text2="" Text3="" />
			<Param Out="" Type="1" Text1="Character Modeling Artist" Text2="" Text3="" />
			<Param Out="" Type="4" Text1="" Text2="Aiko Komamura" Text3="" />
			<Param Out="" Type="4" Text1="" Text2="Airi Ono" Text3="" />
			<Param Out="" Type="4" Text1="" Text2="Alsun" Text3="" />
			<Param Out="" Type="4" Text1="" Text2="Daisuke Suzuki" Text3="" />
			<Param Out="" Type="4" Text1="" Text2="Hiroto Shibata" Text3="" />
			<Param Out="" Type="4" Text1="" Text2="Kazuhito Nakamura" Text3="" />
			<Param Out="" Type="4" Text1="" Text2="Koji Futahashi" Text3="" />
			<Param Out="" Type="4" Text1="" Text2="Mitsuharu Fushie" Text3="" />
			<Param Out="" Type="4" Text1="" Text2="Ruka Teragishi" Text3="" />
			<Param Out="" Type="4" Text1="" Text2="Seiya Tamura" Text3="" />
			<Param Out="" Type="4" Text1="" Text2="Svein-Arne Hartveit" Text3="" />
			<Param Out="" Type="4" Text1="" Text2="Tetsuya Sasaki" Text3="" />
			<Param Out="" Type="10" Text1="" Text2="" Text3="" />
			<Param Out="" Type="1" Text1="Look Development Artist" Text2="" Text3="" />
			<Param Out="" Type="2" Text1="" Text2="Aika Yoshida" Text3="" />
			<Param Out="" Type="10" Text1="" Text2="" Text3="" />
			<Param Out="" Type="1" Text1="Environment Supervisor" Text2="" Text3="" />
			<Param Out="" Type="2" Text1="" Text2="Akihiro Matsuo" Text3="" />
			<Param Out="" Type="10" Text1="" Text2="" Text3="" />
			<Param Out="" Type="1" Text1="Environment Artist" Text2="" Text3="" />
			<Param Out="" Type="4" Text1="" Text2="Miyuki Kobayashi" Text3="" />
			<Param Out="" Type="4" Text1="" Text2="Naoki Kumazawa" Text3="" />
			<Param Out="" Type="4" Text1="" Text2="Nobunao Ono" Text3="" />
			<Param Out="" Type="10" Text1="" Text2="" Text3="" />
			<Param Out="" Type="1" Text1="Props &amp; Weapons Supervisor" Text2="" Text3="" />
			<Param Out="" Type="2" Text1="" Text2="Shinji Tsutsumi" Text3="" />
			<Param Out="" Type="10" Text1="" Text2="" Text3="" />
			<Param Out="" Type="1" Text1="Props &amp; Weapons Artist" Text2="" Text3="" />
			<Param Out="" Type="2" Text1="" Text2="Yusuke Matsuda" Text3="" />
			<Param Out="" Type="10" Text1="" Text2="" Text3="" />
			<Param Out="" Type="1" Text1="Rigging Supervisor" Text2="" Text3="" />
			<Param Out="" Type="2" Text1="" Text2="Miquel Campos" Text3="" />
			<Param Out="" Type="10" Text1="" Text2="" Text3="" />
			<Param Out="" Type="1" Text1="Rigging Artist" Text2="" Text3="" />
			<Param Out="" Type="3" Text1="" Text2="Ai Takeuchi" Text3="" />
			<Param Out="" Type="3" Text1="" Text2="Hiroyuki Tokudome" Text3="" />
			<Param Out="" Type="3" Text1="" Text2="Sadanori Kusakari" Text3="" />
			<Param Out="" Type="3" Text1="" Text2="Soh Choong Leong" Text3="" />
			<Param Out="" Type="10" Text1="" Text2="" Text3="" />
			<Param Out="" Type="1" Text1="Animation Supervisor" Text2="" Text3="" />
			<Param Out="" Type="2" Text1="" Text2="Hiroo Miwa" Text3="" />
			<Param Out="" Type="10" Text1="" Text2="" Text3="" />
			<Param Out="" Type="1" Text1="Technical Animation Supervisor" Text2="" Text3="" />
			<Param Out="" Type="3" Text1="" Text2="Masashi Matsumoto" Text3="" />
			<Param Out="" Type="3" Text1="" Text2="Norihide Higashimura" Text3="" />
			<Param Out="" Type="10" Text1="" Text2="" Text3="" />
			<Param Out="" Type="1" Text1="Lead Animator" Text2="" Text3="" />
			<Param Out="" Type="3" Text1="" Text2="Tadashi Fujita" Text3="" />
			<Param Out="" Type="3" Text1="" Text2="Tsuyoshi Nishikawa" Text3="" />
			<Param Out="" Type="10" Text1="" Text2="" Text3="" />
			<Param Out="" Type="1" Text1="Lead Facial Animator" Text2="" Text3="" />
			<Param Out="" Type="2" Text1="" Text2="Takahiro Miura" Text3="" />
			<Param Out="" Type="10" Text1="" Text2="" Text3="" />
			<Param Out="" Type="1" Text1="Animator" Text2="" Text3="" />
			<Param Out="" Type="4" Text1="" Text2="Aimi Suda" Text3="" />
			<Param Out="" Type="4" Text1="" Text2="Aya Yamaguchi" Text3="" />
			<Param Out="" Type="4" Text1="" Text2="Daiki Tanaka" Text3="" />
			<Param Out="" Type="4" Text1="" Text2="Hidekazu Yamada" Text3="" />
			<Param Out="" Type="4" Text1="" Text2="Hiroshi Kajiyama" Text3="" />
			<Param Out="" Type="4" Text1="" Text2="Kaito Ooki" Text3="" />
			<Param Out="" Type="4" Text1="" Text2="Kazuki Kitamura" Text3="" />
			<Param Out="" Type="4" Text1="" Text2="Kazuto Yasuda" Text3="" />
			<Param Out="" Type="4" Text1="" Text2="Kentarou Narimatsu" Text3="" />
			<Param Out="" Type="4" Text1="" Text2="Ko Mogi" Text3="" />
			<Param Out="" Type="4" Text1="" Text2="Kohei Otsuka" Text3="" />
			<Param Out="" Type="4" Text1="" Text2="Kuniharu Koike" Text3="" />
			<Param Out="" Type="4" Text1="" Text2="Makoto Seki" Text3="" />
			<Param Out="" Type="4" Text1="" Text2="Manabu Konno" Text3="" />
			<Param Out="" Type="4" Text1="" Text2="Masato Tanabe" Text3="" />
			<Param Out="" Type="4" Text1="" Text2="Mayumi Kawanishi" Text3="" />
			<Param Out="" Type="4" Text1="" Text2="Naoki Terada" Text3="" />
			<Param Out="" Type="4" Text1="" Text2="Ryo Tsukagoshi" Text3="" />
			<Param Out="" Type="4" Text1="" Text2="Shiori Nakatani" Text3="" />
			<Param Out="" Type="4" Text1="" Text2="Shunta Tanaka" Text3="" />
			<Param Out="" Type="4" Text1="" Text2="Takayuki Shigekawa" Text3="" />
			<Param Out="" Type="4" Text1="" Text2="Takeshi Saga" Text3="" />
			<Param Out="" Type="4" Text1="" Text2="Wu Shan-Kai" Text3="" />
			<Param Out="" Type="4" Text1="" Text2="Yang Yuanjie" Text3="" />
			<Param Out="" Type="4" Text1="" Text2="Yukiko Suzuki" Text3="" />
			<Param Out="" Type="10" Text1="" Text2="" Text3="" />
			<Param Out="" Type="1" Text1="Effects Supervisor" Text2="" Text3="" />
			<Param Out="" Type="2" Text1="" Text2="Noriaki Maruyama" Text3="" />
			<Param Out="" Type="10" Text1="" Text2="" Text3="" />
			<Param Out="" Type="1" Text1="Lead Effects Artist" Text2="" Text3="" />
			<Param Out="" Type="4" Text1="" Text2="Kei Shiozawa" Text3="" />
			<Param Out="" Type="4" Text1="" Text2="Koji Kawamura" Text3="" />
			<Param Out="" Type="4" Text1="" Text2="Yusuke Nakamura" Text3="" />
			<Param Out="" Type="10" Text1="" Text2="" Text3="" />
			<Param Out="" Type="1" Text1="Effects Artist" Text2="" Text3="" />
			<Param Out="" Type="4" Text1="" Text2="Katsuyoshi Yoshizawa" Text3="" />
			<Param Out="" Type="4" Text1="" Text2="Kensei Fujie" Text3="" />
			<Param Out="" Type="4" Text1="" Text2="Matthew Einstein Britto" Text3="" />
			<Param Out="" Type="4" Text1="" Text2="Miki Kanai" Text3="" />
			<Param Out="" Type="4" Text1="" Text2="Ren Kikuchi" Text3="" />
			<Param Out="" Type="4" Text1="" Text2="Wang Yuhai" Text3="" />
			<Param Out="" Type="4" Text1="" Text2="Yuki Sato" Text3="" />
			<Param Out="" Type="10" Text1="" Text2="" Text3="" />
			<Param Out="" Type="1" Text1="Crowd TD" Text2="" Text3="" />
			<Param Out="" Type="3" Text1="" Text2="Katsunori Ishii" Text3="" />
			<Param Out="" Type="3" Text1="" Text2="Seita Matsumoto" Text3="" />
			<Param Out="" Type="10" Text1="" Text2="" Text3="" />
			<Param Out="" Type="1" Text1="Lighting &amp; Composite Supervisor" Text2="" Text3="" />
			<Param Out="" Type="2" Text1="" Text2="Ronny Sun" Text3="" />
			<Param Out="" Type="10" Text1="" Text2="" Text3="" />
			<Param Out="" Type="1" Text1="Lead Lighting &amp; Composite Artist" Text2="" Text3="" />
			<Param Out="" Type="3" Text1="" Text2="Kazuma Mizutani" Text3="" />
			<Param Out="" Type="3" Text1="" Text2="Kazuo Mitsuyama" Text3="" />
			<Param Out="" Type="3" Text1="" Text2="Satoshi Okubo" Text3="" />
			<Param Out="" Type="3" Text1="" Text2="Yukie Nakajima" Text3="" />
			<Param Out="" Type="10" Text1="" Text2="" Text3="" />
			<Param Out="" Type="1" Text1="Lighting &amp; Composite Artist" Text2="" Text3="" />
			<Param Out="" Type="4" Text1="" Text2="Frank Jozsef Medgyesy" Text3="" />
			<Param Out="" Type="4" Text1="" Text2="Haruka Kakuta" Text3="" />
			<Param Out="" Type="4" Text1="" Text2="Jun Yabuki" Text3="" />
			<Param Out="" Type="4" Text1="" Text2="Kanami Otake" Text3="" />
			<Param Out="" Type="4" Text1="" Text2="Li Yiyang" Text3="" />
			<Param Out="" Type="4" Text1="" Text2="Marine Boudry" Text3="" />
			<Param Out="" Type="4" Text1="" Text2="Masayoshi Ozawa" Text3="" />
			<Param Out="" Type="4" Text1="" Text2="Nimisha Prem" Text3="" />
			<Param Out="" Type="4" Text1="" Text2="Ryotaro Mano" Text3="" />
			<Param Out="" Type="4" Text1="" Text2="Syunosuke Nakano" Text3="" />
			<Param Out="" Type="4" Text1="" Text2="Tatsuya Mihara" Text3="" />
			<Param Out="" Type="4" Text1="" Text2="Toru Okazawa" Text3="" />
			<Param Out="" Type="10" Text1="" Text2="" Text3="" />
			<Param Out="" Type="1" Text1="Grand OP Director" Text2="" Text3="" />
			<Param Out="" Type="2" Text1="" Text2="Shunsuke Tsuchiya" Text3="" />
			<Param Out="" Type="10" Text1="" Text2="" Text3="" />
			<Param Out="" Type="1" Text1="Grand OP Animator" Text2="" Text3="" />
			<Param Out="" Type="3" Text1="" Text2="Takayuki Shigekawa" Text3="" />
			<Param Out="" Type="3" Text1="" Text2="Tsuyoshi Tanaka" Text3="" />
			<Param Out="" Type="10" Text1="" Text2="" Text3="" />
			<Param Out="" Type="1" Text1="Grand OP Editor" Text2="" Text3="" />
			<Param Out="" Type="2" Text1="" Text2="Shun Tokuda" Text3="" />
			<Param Out="" Type="10" Text1="" Text2="" Text3="" />
			<Param Out="" Type="1" Text1="Pipeline Engineer" Text2="" Text3="" />
			<Param Out="" Type="4" Text1="" Text2="Gabriella Villar" Text3="" />
			<Param Out="" Type="4" Text1="" Text2="Kenichi Yoshida" Text3="" />
			<Param Out="" Type="4" Text1="" Text2="Rafael Villar" Text3="" />
			<Param Out="" Type="10" Text1="" Text2="" Text3="" />
			<Param Out="" Type="1" Text1="Production Engineer" Text2="" Text3="" />
			<Param Out="" Type="4" Text1="" Text2="Makoto Oda" Text3="" />
			<Param Out="" Type="4" Text1="" Text2="Noboru Fujiyama" Text3="" />
			<Param Out="" Type="4" Text1="" Text2="Yoshiyuki Endo" Text3="" />
			<Param Out="" Type="10" Text1="" Text2="" Text3="" />
			<Param Out="" Type="1" Text1="System Engineer" Text2="" Text3="" />
			<Param Out="" Type="3" Text1="" Text2="Hisashi Ogasawara" Text3="" />
			<Param Out="" Type="3" Text1="" Text2="Yuuki Shimizu" Text3="" />
			<Param Out="" Type="10" Text1="" Text2="" Text3="" />
			<Param Out="" Type="1" Text1="Production Manager" Text2="" Text3="" />
			<Param Out="" Type="3" Text1="" Text2="Daisuke Chonan" Text3="" />
			<Param Out="" Type="3" Text1="" Text2="Izumi Nakai" Text3="" />
			<Param Out="" Type="3" Text1="" Text2="Kana Kibe" Text3="" />
			<Param Out="" Type="3" Text1="" Text2="Kodai Chiyo" Text3="" />
			<Param Out="" Type="10" Text1="" Text2="" Text3="" />
			<Param Out="" Type="1" Text1="Coordinator" Text2="" Text3="" />
			<Param Out="" Type="2" Text1="" Text2="Kaori Nishimoto" Text3="" />
			<Param Out="" Type="10" Text1="" Text2="" Text3="" />
			<Param Out="" Type="1" Text1="Assistant Production Manager" Text2="" Text3="" />
			<Param Out="" Type="2" Text1="" Text2="Tatsuki Kuramochi" Text3="" />
			<Param Out="" Type="10" Text1="" Text2="" Text3="" />
			<Param Out="" Type="1" Text1="Translator" Text2="" Text3="" />
			<Param Out="" Type="2" Text1="" Text2="Naoko Umetsu" Text3="" />
			<Param Out="" Type="10" Text1="" Text2="" Text3="" />
			<Param Out="" Type="1" Text1="Producer" Text2="" Text3="" />
			<Param Out="" Type="2" Text1="" Text2="Takeshi Nagasawa" Text3="" />
			<Param Out="" Type="10" Text1="" Text2="" Text3="" />
			<Param Out="" Type="1" Text1="Animation Produced by" Text2="" Text3="" />
			<Param Out="" Type="2" Text1="" Text2="ANIMA" Text3="" />
			<Param Out="" Type="12" Text1="" Text2="" Text3="" />
			<Param Out="" Type="8" Text1="TYUTYU.Ltd" Text2="" Text3="" />
			<Param Out="" Type="1" Text1="Storyboard Artist" Text2="" Text3="" />
			<Param Out="" Type="4" Text1="" Text2="Akemi Nakashima" Text3="" />
			<Param Out="" Type="4" Text1="" Text2="Hitomi Kakinoki" Text3="" />
			<Param Out="" Type="4" Text1="" Text2="Chisaki Sato" Text3="" />
			<Param Out="" Type="12" Text1="" Text2="" Text3="" />
			<Param Out="" Type="8" Text1="Just Cause Productions, Inc." Text2="" Text3="" />
			<Param Out="" Type="1" Text1="Previs Producer" Text2="" Text3="" />
			<Param Out="" Type="2" Text1="" Text2="Takuya Shibata" Text3="" />
			<Param Out="" Type="10" Text1="" Text2="" Text3="" />
			<Param Out="" Type="1" Text1="Previs Director" Text2="" Text3="" />
			<Param Out="" Type="2" Text1="" Text2="Masanori Kobayashi" Text3="" />
			<Param Out="" Type="10" Text1="" Text2="" Text3="" />
			<Param Out="" Type="1" Text1="Animation Supervisor" Text2="" Text3="" />
			<Param Out="" Type="2" Text1="" Text2="Masaaki Bizen" Text3="" />
			<Param Out="" Type="10" Text1="" Text2="" Text3="" />
			<Param Out="" Type="1" Text1="Animator" Text2="" Text3="" />
			<Param Out="" Type="3" Text1="" Text2="Mayuko Shibata" Text3="" />
			<Param Out="" Type="3" Text1="" Text2="Keisuke Saito" Text3="" />
			<Param Out="" Type="10" Text1="" Text2="" Text3="" />
			<Param Out="" Type="1" Text1="Production Assistant" Text2="" Text3="" />
			<Param Out="" Type="2" Text1="" Text2="Shunichiro Ikeda" Text3="" />
			<Param Out="" Type="12" Text1="" Text2="" Text3="" />
			<Param Out="" Type="8" Text1="Studio Hotaru,Inc" Text2="" Text3="" />
			<Param Out="" Type="1" Text1="Character Modeling Supervisor" Text2="" Text3="" />
			<Param Out="" Type="2" Text1="" Text2="Kito Ogihara" Text3="" />
			<Param Out="" Type="10" Text1="" Text2="" Text3="" />
			<Param Out="" Type="1" Text1="Character Modeling Artist" Text2="" Text3="" />
			<Param Out="" Type="3" Text1="" Text2="Yuma Ito" Text3="" />
			<Param Out="" Type="3" Text1="" Text2="Taku Nemoto" Text3="" />
			<Param Out="" Type="12" Text1="" Text2="" Text3="" />
			<Param Out="" Type="8" Text1="GriotGroove Inc." Text2="" Text3="" />
			<Param Out="" Type="1" Text1="Lead Character Modeling Artist" Text2="" Text3="" />
			<Param Out="" Type="2" Text1="" Text2="Yuta Tomoto" Text3="" />
			<Param Out="" Type="10" Text1="" Text2="" Text3="" />
			<Param Out="" Type="1" Text1="CG Artist" Text2="" Text3="" />
			<Param Out="" Type="4" Text1="" Text2="Hiroshi Kataoka" Text3="" />
			<Param Out="" Type="4" Text1="" Text2="Yoshihiko Yamaguchi" Text3="" />
			<Param Out="" Type="4" Text1="" Text2="Kento Ebisawa" Text3="" />
			<Param Out="" Type="10" Text1="" Text2="" Text3="" />
			<Param Out="" Type="1" Text1="Producer" Text2="" Text3="" />
			<Param Out="" Type="2" Text1="" Text2="Yuta Goto" Text3="" />
			<Param Out="" Type="12" Text1="" Text2="" Text3="" />
			<Param Out="" Type="8" Text1="huhaa" Text2="" Text3="" />
			<Param Out="" Type="1" Text1="Rigging Artist" Text2="" Text3="" />
			<Param Out="" Type="3" Text1="" Text2="Juan Muñoz" Text3="" />
			<Param Out="" Type="3" Text1="" Text2="Ignacio Santalla" Text3="" />
			<Param Out="" Type="12" Text1="" Text2="" Text3="" />
			<Param Out="" Type="8" Text1="GEMBA" Text2="" Text3="" />
			<Param Out="" Type="1" Text1="Environment Artist" Text2="" Text3="" />
			<Param Out="" Type="2" Text1="" Text2="Kotaro Arai" Text3="" />
			<Param Out="" Type="10" Text1="" Text2="" Text3="" />
			<Param Out="" Type="1" Text1="Animation Supervisor" Text2="" Text3="" />
			<Param Out="" Type="2" Text1="" Text2="Hisashi Egawa" Text3="" />
			<Param Out="" Type="10" Text1="" Text2="" Text3="" />
			<Param Out="" Type="1" Text1="Lead Grand OP Animator" Text2="" Text3="" />
			<Param Out="" Type="2" Text1="" Text2="Shunsuke Miyazawa" Text3="" />
			<Param Out="" Type="10" Text1="" Text2="" Text3="" />
			<Param Out="" Type="1" Text1="Grand OP Animator" Text2="" Text3="" />
			<Param Out="" Type="4" Text1="" Text2="Yasuhiro Hattori" Text3="" />
			<Param Out="" Type="4" Text1="" Text2="Airi Kobayashi" Text3="" />
			<Param Out="" Type="4" Text1="" Text2="Yukiho Nishimoto" Text3="" />
			<Param Out="" Type="4" Text1="" Text2="Shuhei Yokoyama" Text3="" />
			<Param Out="" Type="4" Text1="" Text2="Masaki Morikawa" Text3="" />
			<Param Out="" Type="4" Text1="" Text2="Minaho Tanaka" Text3="" />
			<Param Out="" Type="10" Text1="" Text2="" Text3="" />
			<Param Out="" Type="1" Text1="Production Manager" Text2="" Text3="" />
			<Param Out="" Type="4" Text1="" Text2="lixue" Text3="" />
			<Param Out="" Type="4" Text1="" Text2="Keisuke Kobayashi" Text3="" />
			<Param Out="" Type="4" Text1="" Text2="Ayaka Ishizuka" Text3="" />
			<Param Out="" Type="10" Text1="" Text2="" Text3="" />
			<Param Out="" Type="1" Text1="Producer" Text2="" Text3="" />
			<Param Out="" Type="2" Text1="" Text2="Toshiki Niidome" Text3="" />
			<Param Out="" Type="12" Text1="" Text2="" Text3="" />
			<Param Out="" Type="8" Text1="Creative Freaks Inc." Text2="" Text3="" />
			<Param Out="" Type="1" Text1="Background Art Director" Text2="" Text3="" />
			<Param Out="" Type="2" Text1="" Text2="Nguyen Ngoc Hoang" Text3="" />
			<Param Out="" Type="10" Text1="" Text2="" Text3="" />
			<Param Out="" Type="1" Text1="Lead Background Artist" Text2="" Text3="" />
			<Param Out="" Type="3" Text1="" Text2="Nguyen Ngoc Thanh" Text3="" />
			<Param Out="" Type="3" Text1="" Text2="Attachai Boonsmai" Text3="" />
			<Param Out="" Type="10" Text1="" Text2="" Text3="" />
			<Param Out="" Type="1" Text1="Background Artist" Text2="" Text3="" />
			<Param Out="" Type="4" Text1="" Text2="Adited Mechaijreonying" Text3="" />
			<Param Out="" Type="4" Text1="" Text2="Parinya Phetwiphat " Text3="" />
			<Param Out="" Type="4" Text1="" Text2="Yosanann Rujichayakhun" Text3="" />
			<Param Out="" Type="4" Text1="" Text2="Truong Hoang Long" Text3="" />
			<Param Out="" Type="4" Text1="" Text2="To Nguyen Ngoc Huyen" Text3="" />
			<Param Out="" Type="4" Text1="" Text2="Nguyen Thai Hoa" Text3="" />
			<Param Out="" Type="10" Text1="" Text2="" Text3="" />
			<Param Out="" Type="1" Text1="Director &amp; Manager" Text2="" Text3="" />
			<Param Out="" Type="2" Text1="" Text2="Mineaki Sugata" Text3="" />
			<Param Out="" Type="12" Text1="" Text2="" Text3="" />
			<Param Out="" Type="8" Text1="quack-luck Inc." Text2="" Text3="" />
			<Param Out="" Type="1" Text1="Motion Actor" Text2="" Text3="" />
			<Param Out="" Type="3" Text1="" Text2="Kai Kitamura" Text3="" />
			<Param Out="" Type="3" Text1="" Text2="Ami Ikenaga" Text3="" />
			<Param Out="" Type="3" Text1="" Text2="Ryosuke Kato" Text3="" />
			<Param Out="" Type="3" Text1="" Text2="Naomi Taniyama" Text3="" />
			<Param Out="" Type="12" Text1="" Text2="" Text3="" />
			<Param Out="" Type="8" Text1="KATSUGEKIZA Inc." Text2="" Text3="" />
			<Param Out="" Type="1" Text1="Motion Actor" Text2="" Text3="" />
			<Param Out="" Type="3" Text1="" Text2="Takahiro Homma" Text3="" />
			<Param Out="" Type="3" Text1="" Text2="Hidetaka Ichiyama" Text3="" />
			<Param Out="" Type="3" Text1="" Text2="Umi Tanoue" Text3="" />
			<Param Out="" Type="3" Text1="" Text2="Yuka Hino" Text3="" />
			<Param Out="" Type="10" Text1="" Text2="" Text3="" />
			<Param Out="" Type="1" Text1="Action Coordinator" Text2="" Text3="" />
			<Param Out="" Type="2" Text1="" Text2="Wataru Koga" Text3="" />
			<Param Out="" Type="12" Text1="" Text2="" Text3="" />
			<Param Out="" Type="8" Text1="d/visual Inc." Text2="" Text3="" />
			<Param Out="" Type="1" Text1="CG Supervisor" Text2="" Text3="" />
			<Param Out="" Type="2" Text1="" Text2="Hideo Mori" Text3="" />
			<Param Out="" Type="10" Text1="" Text2="" Text3="" />
			<Param Out="" Type="1" Text1="Animation Supervisor" Text2="" Text3="" />
			<Param Out="" Type="2" Text1="" Text2="Watit Prommi" Text3="" />
			<Param Out="" Type="10" Text1="" Text2="" Text3="" />
			<Param Out="" Type="1" Text1="Senior Animator" Text2="" Text3="" />
			<Param Out="" Type="3" Text1="" Text2="Jiranan Wongsilakij" Text3="" />
			<Param Out="" Type="3" Text1="" Text2="Ratchawat Srithong" Text3="" />
			<Param Out="" Type="10" Text1="" Text2="" Text3="" />
			<Param Out="" Type="1" Text1="Animator" Text2="" Text3="" />
			<Param Out="" Type="3" Text1="" Text2="Juladit Changnak" Text3="" />
			<Param Out="" Type="3" Text1="" Text2="Teeradach Deelin" Text3="" />
			<Param Out="" Type="10" Text1="" Text2="" Text3="" />
			<Param Out="" Type="1" Text1="VFX Supervisor" Text2="" Text3="" />
			<Param Out="" Type="2" Text1="" Text2="Apiwat Jannarumit" Text3="" />
			<Param Out="" Type="10" Text1="" Text2="" Text3="" />
			<Param Out="" Type="1" Text1="Senior VFX Artist" Text2="" Text3="" />
			<Param Out="" Type="3" Text1="" Text2="Jukgapong Chuaysuk" Text3="" />
			<Param Out="" Type="3" Text1="" Text2="Wiroon Chamwichitto" Text3="" />
			<Param Out="" Type="10" Text1="" Text2="" Text3="" />
			<Param Out="" Type="1" Text1="Production Coordinator" Text2="" Text3="" />
			<Param Out="" Type="3" Text1="" Text2="Tsubasa Fujii" Text3="" />
			<Param Out="" Type="3" Text1="" Text2="Phunyapat Poolperm" Text3="" />
			<Param Out="" Type="10" Text1="" Text2="" Text3="" />
			<Param Out="" Type="1" Text1="Producer" Text2="" Text3="" />
			<Param Out="" Type="4" Text1="" Text2="Colpi Federico" Text3="" />
			<Param Out="" Type="4" Text1="" Text2="Yusuke Ogura" Text3="" />
			<Param Out="" Type="4" Text1="" Text2="Saksiri Koshpasharin" Text3="" />
			<Param Out="" Type="12" Text1="" Text2="" Text3="" />
			<Param Out="" Type="8" Text1="StealthWorks. Inc." Text2="" Text3="" />
			<Param Out="" Type="1" Text1="FX Supervisor" Text2="" Text3="" />
			<Param Out="" Type="2" Text1="" Text2="Suguru Nogami" Text3="" />
			<Param Out="" Type="10" Text1="" Text2="" Text3="" />
			<Param Out="" Type="1" Text1="Line Producer" Text2="" Text3="" />
			<Param Out="" Type="2" Text1="" Text2="Shinya Kohno" Text3="" />
			<Param Out="" Type="10" Text1="" Text2="" Text3="" />
			<Param Out="" Type="1" Text1="Lead FX Technical Director" Text2="" Text3="" />
			<Param Out="" Type="3" Text1="" Text2="Kei Yoneoka" Text3="" />
			<Param Out="" Type="3" Text1="" Text2="Yuki Ochiai" Text3="" />
			<Param Out="" Type="10" Text1="" Text2="" Text3="" />
			<Param Out="" Type="1" Text1="FX Technical Director" Text2="" Text3="" />
			<Param Out="" Type="4" Text1="" Text2="Nobuo Eijima" Text3="" />
			<Param Out="" Type="4" Text1="" Text2="Tomoki Miyashita" Text3="" />
			<Param Out="" Type="4" Text1="" Text2="Akira Nakamura" Text3="" />
			<Param Out="" Type="4" Text1="" Text2="Seiya Tsuboyama " Text3="" />
			<Param Out="" Type="4" Text1="" Text2="Kazuma Kasuya " Text3="" />
			<Param Out="" Type="12" Text1="" Text2="" Text3="" />
			<Param Out="" Type="8" Text1="Q-TEC,INC." Text2="" Text3="" />
			<Param Out="" Type="1" Text1="Lighting &amp; Composite Artist" Text2="" Text3="" />
			<Param Out="" Type="3" Text1="" Text2="Kota Sato" Text3="" />
			<Param Out="" Type="3" Text1="" Text2="Asuka Tanaka" Text3="" />
			<Param Out="" Type="10" Text1="" Text2="" Text3="" />
			<Param Out="" Type="1" Text1="Coordinator" Text2="" Text3="" />
			<Param Out="" Type="2" Text1="" Text2="Takahiro Kannae" Text3="" />
			<Param Out="" Type="12" Text1="" Text2="" Text3="" />
			<Param Out="" Type="8" Text1="OMNIBUS JAPAN Inc." Text2="" Text3="" />
			<Param Out="" Type="1" Text1="CG Supervisor" Text2="" Text3="" />
			<Param Out="" Type="2" Text1="" Text2="Hirokazu Aoyama" Text3="" />
			<Param Out="" Type="10" Text1="" Text2="" Text3="" />
			<Param Out="" Type="1" Text1="Grand OP Effects Artist" Text2="" Text3="" />
			<Param Out="" Type="2" Text1="" Text2="Kensuke Yuge" Text3="" />
			<Param Out="" Type="10" Text1="" Text2="" Text3="" />
			<Param Out="" Type="1" Text1="Grand OP Lighting &amp; Composite Artist" Text2="" Text3="" />
			<Param Out="" Type="3" Text1="" Text2="Takashi Nishida" Text3="" />
			<Param Out="" Type="3" Text1="" Text2="Masaaki Nakae" Text3="" />
			<Param Out="" Type="3" Text1="" Text2="Hiroyuki Sugibayashi" Text3="" />
			<Param Out="" Type="3" Text1="" Text2="Takashi Yamazaki" Text3="" />
			<Param Out="" Type="10" Text1="" Text2="" Text3="" />
			<Param Out="" Type="1" Text1="Technical Director" Text2="" Text3="" />
			<Param Out="" Type="2" Text1="" Text2="Tetsuya Okuno" Text3="" />
			<Param Out="" Type="10" Text1="" Text2="" Text3="" />
			<Param Out="" Type="1" Text1="Production Manager" Text2="" Text3="" />
			<Param Out="" Type="2" Text1="" Text2="Tetsushi Tanaka" Text3="" />
			<Param Out="" Type="10" Text1="" Text2="" Text3="" />
			<Param Out="" Type="1" Text1="Producer" Text2="" Text3="" />
			<Param Out="" Type="2" Text1="" Text2="Masaki Kikuchi" Text3="" />
			<Param Out="" Type="12" Text1="" Text2="" Text3="" />
			<Param Out="" Type="8" Text1="ImaginaryPower Inc." Text2="" Text3="" />
			<Param Out="" Type="1" Text1="CG Director" Text2="" Text3="" />
			<Param Out="" Type="3" Text1="" Text2="Hiroshi Kometani" Text3="" />
			<Param Out="" Type="3" Text1="" Text2="Tetta Miyazawa" Text3="" />
			<Param Out="" Type="10" Text1="" Text2="" Text3="" />
			<Param Out="" Type="1" Text1="CG Animator" Text2="" Text3="" />
			<Param Out="" Type="2" Text1="" Text2="Ren Takahashi" Text3="" />
			<Param Out="" Type="12" Text1="" Text2="" Text3="" />
			<Param Out="" Type="8" Text1="Leon Studio Inc." Text2="" Text3="" />
			<Param Out="" Type="1" Text1="Producer" Text2="" Text3="" />
			<Param Out="" Type="2" Text1="" Text2="Yuichi Kameyama" Text3="" />
			<Param Out="" Type="12" Text1="" Text2="" Text3="" />
			<Param Out="" Type="8" Text1="Raika Inc." Text2="" Text3="" />
			<Param Out="" Type="1" Text1="Producer" Text2="" Text3="" />
			<Param Out="" Type="2" Text1="" Text2="Hideyuki Saito" Text3="" />
			<Param Out="" Type="12" Text1="" Text2="" Text3="" />
			<Param Out="" Type="8" Text1="Himawari Studio Co.,Ltd" Text2="" Text3="" />
			<Param Out="" Type="1" Text1="Producer" Text2="" Text3="" />
			<Param Out="" Type="2" Text1="" Text2="Yoshitaka Tanigawa" Text3="" />
			<Param Out="" Type="12" Text1="" Text2="" Text3="" />
			<Param Out="" Type="8" Text1="GALAXY OF TERROR CO., Ltd" Text2="" Text3="" />
			<Param Out="" Type="1" Text1="Director" Text2="" Text3="" />
			<Param Out="" Type="2" Text1="" Text2="Kenji Goda" Text3="" />
			<Param Out="" Type="12" Text1="" Text2="" Text3="" />
			<Param Out="" Type="8" Text1="BEE TRIBE CO., LTD." Text2="" Text3="" />
			<Param Out="" Type="1" Text1="Motion Director" Text2="" Text3="" />
			<Param Out="" Type="3" Text1="" Text2="Shinji Utsunomiya" Text3="" />
			<Param Out="" Type="3" Text1="" Text2="Mitsuhiro Kubo" Text3="" />
			<Param Out="" Type="12" Text1="" Text2="" Text3="" />
			<Param Out="" Type="8" Text1="aexinc.Ltd" Text2="" Text3="" />
			<Param Out="" Type="1" Text1="Lead Designer" Text2="" Text3="" />
			<Param Out="" Type="2" Text1="" Text2="Kenji Tsujimura" Text3="" />
			<Param Out="" Type="10" Text1="" Text2="" Text3="" />
			<Param Out="" Type="1" Text1="Designer" Text2="" Text3="" />
			<Param Out="" Type="3" Text1="" Text2="Hitomi Watanabe" Text3="" />
			<Param Out="" Type="3" Text1="" Text2="Chisato Tahara" Text3="" />
			<Param Out="" Type="3" Text1="" Text2="Shizuka Kawasaka" Text3="" />
			<Param Out="" Type="3" Text1="" Text2="Haruka Niiyama" Text3="" />
			<Param Out="" Type="12" Text1="" Text2="" Text3="" />
			<Param Out="" Type="8" Text1="DigisiteGraphics co.,Ltd" Text2="" Text3="" />
			<Param Out="" Type="1" Text1="Lead Designer" Text2="" Text3="" />
			<Param Out="" Type="2" Text1="" Text2="Jinya Kitsui" Text3="" />
			<Param Out="" Type="10" Text1="" Text2="" Text3="" />
			<Param Out="" Type="1" Text1="Lead Animator" Text2="" Text3="" />
			<Param Out="" Type="2" Text1="" Text2="Jumpei Takahashi" Text3="" />
			<Param Out="" Type="10" Text1="" Text2="" Text3="" />
			<Param Out="" Type="1" Text1="Animator" Text2="" Text3="" />
			<Param Out="" Type="4" Text1="" Text2="Hiroyuki Morita" Text3="" />
			<Param Out="" Type="4" Text1="" Text2="Akiho Aiba" Text3="" />
			<Param Out="" Type="4" Text1="" Text2="Hiroaki Iwasaki" Text3="" />
			<Param Out="" Type="4" Text1="" Text2="Tetsuo Arai" Text3="" />
			<Param Out="" Type="4" Text1="" Text2="Meiru Qu" Text3="" />
			<Param Out="" Type="12" Text1="" Text2="" Text3="" />
			<Param Out="" Type="6" Text1="Graphinica,Inc." Text2="" Text3="" />
			<Param Out="" Type="1" Text1="Technical Supervisor" Text2="" Text3="" />
			<Param Out="" Type="2" Text1="" Text2="Akihiro Komiya" Text3="" />
			<Param Out="" Type="10" Text1="" Text2="" Text3="" />
			<Param Out="" Type="1" Text1="Production Coordinator" Text2="" Text3="" />
			<Param Out="" Type="3" Text1="" Text2="Kazuya Tamura" Text3="" />
			<Param Out="" Type="3" Text1="" Text2="Hiroyoshi Suzuki" Text3="" />
			<Param Out="" Type="10" Text1="" Text2="" Text3="" />
			<Param Out="" Type="1" Text1="Lead Animator" Text2="" Text3="" />
			<Param Out="" Type="2" Text1="" Text2="Kyohei Oikawa" Text3="" />
			<Param Out="" Type="10" Text1="" Text2="" Text3="" />
			<Param Out="" Type="1" Text1="Animator" Text2="" Text3="" />
			<Param Out="" Type="4" Text1="" Text2="Saeko Yaginuma" Text3="" />
			<Param Out="" Type="4" Text1="" Text2="Daiki Tsukamoto" Text3="" />
			<Param Out="" Type="4" Text1="" Text2="Haruka Sakaguchi" Text3="" />
			<Param Out="" Type="12" Text1="" Text2="" Text3="" />
			<Param Out="" Type="8" Text1="Graphinica,Inc. Kyoto Studio" Text2="" Text3="" />
			<Param Out="" Type="1" Text1="Animator" Text2="" Text3="" />
			<Param Out="" Type="3" Text1="" Text2="Tsuyoshi Uno" Text3="" />
			<Param Out="" Type="3" Text1="" Text2="Tomomi Sato" Text3="" />
			<Param Out="" Type="12" Text1="" Text2="" Text3="" />
			<Param Out="" Type="8" Text1="OECU JIAMS" Text2="" Text3="" />
			<Param Out="" Type="1" Text1="Mocap Engineer" Text2="" Text3="" />
			<Param Out="" Type="4" Text1="" Text2="Ikumi Teramoto" Text3="" />
			<Param Out="" Type="4" Text1="" Text2="Takafumi Kuze" Text3="" />
			<Param Out="" Type="4" Text1="" Text2="Kiji Morita" Text3="" />
			<Param Out="" Type="12" Text1="" Text2="" Text3="" />
			<Param Out="" Type="8" Text1="Crescent,inc." Text2="" Text3="" />
			<Param Out="" Type="1" Text1="Mocap Supervisor" Text2="" Text3="" />
			<Param Out="" Type="4" Text1="" Text2="Hajime Kotani" Text3="" />
			<Param Out="" Type="4" Text1="" Text2="Miyako Toge" Text3="" />
			<Param Out="" Type="4" Text1="" Text2="Takaya Fukushima" Text3="" />
			<Param Out="" Type="12" Text1="" Text2="" Text3="" />
			<Param Out="" Type="8" Text1="Nakatsuka Kogyo Co., Ltd" Text2="" Text3="" />
			<Param Out="" Type="1" Text1="Mocap Tracker" Text2="" Text3="" />
			<Param Out="" Type="4" Text1="" Text2="Isao Kuromyo" Text3="" />
			<Param Out="" Type="4" Text1="" Text2="Ami Suzawa" Text3="" />
			<Param Out="" Type="4" Text1="" Text2="Rie Yamamoto" Text3="" />
			<Param Out="" Type="4" Text1="" Text2="Yuji Okabe" Text3="" />
			<Param Out="" Type="4" Text1="" Text2="Nobuhiro Ooto" Text3="" />
			<Param Out="" Type="4" Text1="" Text2="Shino Nakatsuka" Text3="" />
			<Param Out="" Type="4" Text1="" Text2="Tatsuya Yamanaka" Text3="" />
			<Param Out="" Type="4" Text1="" Text2="Shogo Yamada " Text3="" />
			<Param Out="" Type="12" Text1="" Text2="" Text3="" />
			<Param Out="" Type="8" Text1="SAKURA WING LLC" Text2="" Text3="" />
			<Param Out="" Type="1" Text1="Motion Actor" Text2="" Text3="" />
			<Param Out="" Type="4" Text1="" Text2="Tsubasa Tada" Text3="" />
			<Param Out="" Type="4" Text1="" Text2="Miki Koyama" Text3="" />
			<Param Out="" Type="4" Text1="" Text2="Yoshinori Tada" Text3="" />
			<Param Out="" Type="4" Text1="" Text2="Daichi Miura" Text3="" />
			<Param Out="" Type="4" Text1="" Text2="Hirifumi Yamaguchi" Text3="" />
			<Param Out="" Type="4" Text1="" Text2="Nagisa Nagae" Text3="" />
			<Param Out="" Type="12" Text1="" Text2="" Text3="" />
			<Param Out="" Type="8" Text1="Unity Technologies Japan K.K." Text2="" Text3="" />
			<Param Out="" Type="1" Text1="Developer Relations Manager/Engineer" Text2="" Text3="" />
			<Param Out="" Type="3" Text1="" Text2="Hideaki Sekiya" Text3="" />
			<Param Out="" Type="3" Text1="" Text2="Yusuke Kurokawa" Text3="" />
			<Param Out="" Type="10" Text1="" Text2="" Text3="" />
			<Param Out="" Type="1" Text1="Developer Relations Engineer" Text2="" Text3="" />
			<Param Out="" Type="2" Text1="" Text2="Yugo Fujioka" Text3="" />
			<Param Out="" Type="10" Text1="" Text2="" Text3="" />
			<Param Out="" Type="1" Text1="Quality Assurance Manager" Text2="" Text3="" />
			<Param Out="" Type="2" Text1="" Text2="Koji Ohno" Text3="" />
			<Param Out="" Type="10" Text1="" Text2="" Text3="" />
			<Param Out="" Type="1" Text1="Senior Software Engineer" Text2="" Text3="" />
			<Param Out="" Type="2" Text1="" Text2="Yusuke Ebata" Text3="" />
			<Param Out="" Type="12" Text1="" Text2="" Text3="" />
			<Param Out="" Type="8" Text1="Being" Text2="" Text3="" />
			<Param Out="" Type="1" Text1="OP Theme Song" Text2="" Text3="" />
			<Param Out="" Type="1" Text1="Vocal" Text2="" Text3="" />
			<Param Out="" Type="2" Text1="" Text2="RYO" Text3="" />
			<Param Out="" Type="10" Text1="" Text2="" Text3="" />
			<Param Out="" Type="1" Text1="ED Theme Song" Text2="" Text3="" />
			<Param Out="" Type="1" Text1="Vocal" Text2="" Text3="" />
			<Param Out="" Type="2" Text1="" Text2="Rainy。" Text3="" />
			<Param Out="" Type="10" Text1="" Text2="" Text3="" />
			<Param Out="" Type="1" Text1="Recording &amp; Mixing Engineer" Text2="" Text3="" />
			<Param Out="" Type="4" Text1="" Text2="Takashi Yoshida" Text3="" />
			<Param Out="" Type="4" Text1="" Text2="Hiroki Sasaki" Text3="" />
			<Param Out="" Type="4" Text1="" Text2="Akinori Nishimura" Text3="" />
			<Param Out="" Type="4" Text1="" Text2="Tokiko Nishimuro" Text3="" />
			<Param Out="" Type="4" Text1="" Text2="Fuminori Asaoka" Text3="" />
			<Param Out="" Type="12" Text1="" Text2="" Text3="" />
			<Param Out="" Type="1" Text1="Debug" Text2="" Text3="" />
			<Param Out="" Type="8" Text1="Mario Club Co., Ltd." Text2="" Text3="" />
			<Param Out="" Type="4" Text1="" Text2="Tsuyoshi Komura" Text3="" />
			<Param Out="" Type="4" Text1="" Text2="Masaharu Shima" Text3="" />
			<Param Out="" Type="4" Text1="" Text2="Takaaki Ueno" Text3="" />
			<Param Out="" Type="4" Text1="" Text2="Hiroyuki Matsubara" Text3="" />
			<Param Out="" Type="4" Text1="" Text2="Osamu Mizuochi" Text3="" />
			<Param Out="" Type="4" Text1="" Text2="Kenta Hamamoto" Text3="" />
			<Param Out="" Type="4" Text1="" Text2="Masayuki Hama" Text3="" />
			<Param Out="" Type="4" Text1="" Text2="Ryotaro Hayashi" Text3="" />
			<Param Out="" Type="10" Text1="" Text2="" Text3="" />
			<Param Out="" Type="8" Text1="DIGITAL HEARTS Co., Ltd." Text2="" Text3="" />
			<Param Out="" Type="4" Text1="" Text2="Shinpei Otowa" Text3="" />
			<Param Out="" Type="4" Text1="" Text2="Osamu Furuta" Text3="" />
			<Param Out="" Type="4" Text1="" Text2="Soichiro Fujita" Text3="" />
			<Param Out="" Type="4" Text1="" Text2="Wataru Matsushita" Text3="" />
			<Param Out="" Type="4" Text1="" Text2="Taishi Mukaigawara" Text3="" />
			<Param Out="" Type="4" Text1="" Text2="Tetsushi Tanabe" Text3="" />
			<Param Out="" Type="4" Text1="" Text2="Masatoshi Nakamura" Text3="" />
			<Param Out="" Type="4" Text1="" Text2="Shintaro Nishiguchi" Text3="" />
			<Param Out="" Type="4" Text1="" Text2="Yusuke Suzuki" Text3="" />
			<Param Out="" Type="4" Text1="" Text2="Shoichiro Kaku" Text3="" />
			<Param Out="" Type="4" Text1="" Text2="Kazuki Hoshi" Text3="" />
			<Param Out="" Type="10" Text1="" Text2="" Text3="" />
			<Param Out="" Type="2" Text1="" Text2="Mario Club Co., Ltd." Text3="" />
			<Param Out="" Type="2" Text1="" Text2="DIGITAL HEARTS Co., Ltd." Text3="" />
			<Param Out="" Type="12" Text1="" Text2="" Text3="" />
			<Param Out="" Type="8" Text1="NOA Staff" Text2="" Text3="" />
			<Param Out="" Type="1" Text1="Localization Management" Text2="" Text3="" />
			<Param Out="" Type="4" Text1="" Text2="Reiko Ninomiya" Text3="" />
			<Param Out="" Type="4" Text1="" Text2="Rich Amtower" Text3="" />
			<Param Out="" Type="4" Text1="" Text2="Erika Webright Arlot" Text3="" />
			<Param Out="" Type="4" Text1="" Text2="Michael Benedetto" Text3="" />
			<Param Out="" Type="4" Text1="" Text2="Nicko Gonzalez De Santiago" Text3="" />
			<Param Out="" Type="4" Text1="" Text2="Ann Lin" Text3="" />
			<Param Out="" Type="4" Text1="" Text2="Tim O'Leary" Text3="" />
			<Param Out="" Type="4" Text1="" Text2="Scot Ritchey" Text3="" />
			<Param Out="" Type="4" Text1="" Text2="Morgan Ritchie" Text3="" />
			<Param Out="" Type="4" Text1="" Text2="Álex Zarza" Text3="" />
			<Param Out="" Type="10" Text1="" Text2="" Text3="" />
			<Param Out="" Type="1" Text1="NOA Localization" Text2="" Text3="" />
			<Param Out="" Type="4" Text1="" Text2="Ana Celeste Ascanio" Text3="" />
			<Param Out="" Type="4" Text1="" Text2="Winda Benedetti" Text3="" />
			<Param Out="" Type="4" Text1="" Text2="Gab Bergollo Drouyn" Text3="" />
			<Param Out="" Type="4" Text1="" Text2="Kay Cal" Text3="" />
			<Param Out="" Type="4" Text1="" Text2="Yanett Cepeda Valor" Text3="" />
			<Param Out="" Type="4" Text1="" Text2="Rosa Cogley" Text3="" />
			<Param Out="" Type="4" Text1="" Text2="Owen Cooney" Text3="" />
			<Param Out="" Type="4" Text1="" Text2="Andrea Cox" Text3="" />
			<Param Out="" Type="4" Text1="" Text2="Rhiona Dey" Text3="" />
			<Param Out="" Type="4" Text1="" Text2="Ethan Dill" Text3="" />
			<Param Out="" Type="4" Text1="" Text2="Katie Dunlop" Text3="" />
			<Param Out="" Type="4" Text1="" Text2="Raymond Elliget" Text3="" />
			<Param Out="" Type="4" Text1="" Text2="Yunica Hara" Text3="" />
			<Param Out="" Type="4" Text1="" Text2="Daniel Harris" Text3="" />
			<Param Out="" Type="4" Text1="" Text2="Rob Heiret" Text3="" />
			<Param Out="" Type="4" Text1="" Text2="Paloma Hernandez" Text3="" />
			<Param Out="" Type="4" Text1="" Text2="Sara Hoad" Text3="" />
			<Param Out="" Type="4" Text1="" Text2="Bill Hutchens" Text3="" />
			<Param Out="" Type="4" Text1="" Text2="Ryan Kelley" Text3="" />
			<Param Out="" Type="4" Text1="" Text2="Ryan Kindel" Text3="" />
			<Param Out="" Type="4" Text1="" Text2="Lars Knudson" Text3="" />
			<Param Out="" Type="4" Text1="" Text2="Brandon Kraemer" Text3="" />
			<Param Out="" Type="4" Text1="" Text2="Christelle Liviero Aracena" Text3="" />
			<Param Out="" Type="4" Text1="" Text2="Nich Maragos" Text3="" />
			<Param Out="" Type="4" Text1="" Text2="Yoriko Marusich" Text3="" />
			<Param Out="" Type="4" Text1="" Text2="Karina Mora" Text3="" />
			<Param Out="" Type="4" Text1="" Text2="Kento Oiwa" Text3="" />
			<Param Out="" Type="4" Text1="" Text2="Carolina Quesada" Text3="" />
			<Param Out="" Type="4" Text1="" Text2="Brian Reed" Text3="" />
			<Param Out="" Type="4" Text1="" Text2="Karen Ressler" Text3="" />
			<Param Out="" Type="4" Text1="" Text2="Verónica M. Reyes Peña" Text3="" />
			<Param Out="" Type="4" Text1="" Text2="Audrey Drake Rigg" Text3="" />
			<Param Out="" Type="4" Text1="" Text2="Jennifer Rose" Text3="" />
			<Param Out="" Type="4" Text1="" Text2="Elin Rummel" Text3="" />
			<Param Out="" Type="4" Text1="" Text2="Paul Scheible" Text3="" />
			<Param Out="" Type="4" Text1="" Text2="Ludovic Tientcheu Ponkin" Text3="" />
			<Param Out="" Type="4" Text1="" Text2="Kindra Timmerwilke" Text3="" />
			<Param Out="" Type="4" Text1="" Text2="Marcia Toledo" Text3="" />
			<Param Out="" Type="4" Text1="" Text2="Scott Willson" Text3="" />
			<Param Out="" Type="4" Text1="" Text2="Thaddee Wiseur" Text3="" />
			<Param Out="" Type="10" Text1="" Text2="" Text3="" />
			<Param Out="" Type="1" Text1="Localization Support" Text2="" Text3="" />
			<Param Out="" Type="2" Text1="" Text2="Miya Seeley" Text3="" />
			<Param Out="" Type="10" Text1="" Text2="" Text3="" />
			<Param Out="" Type="1" Text1="NOA Product Testing" Text2="" Text3="" />
			<Param Out="" Type="4" Text1="" Text2="Kentaro Nishimura" Text3="" />
			<Param Out="" Type="4" Text1="" Text2="Kirk Buchanan" Text3="" />
			<Param Out="" Type="4" Text1="" Text2="Tomo Ishiyama" Text3="" />
			<Param Out="" Type="4" Text1="" Text2="Hitoshi Nishizawa" Text3="" />
			<Param Out="" Type="4" Text1="" Text2="Q Dequina" Text3="" />
			<Param Out="" Type="4" Text1="" Text2="Tomoko Mikami" Text3="" />
			<Param Out="" Type="4" Text1="" Text2="Zac Evans" Text3="" />
			<Param Out="" Type="4" Text1="" Text2="Ivan Samoilov" Text3="" />
			<Param Out="" Type="4" Text1="" Text2="Na'jee Jackson" Text3="" />
			<Param Out="" Type="4" Text1="" Text2="Makiko Szolas" Text3="" />
			<Param Out="" Type="4" Text1="" Text2="Madison Levitan" Text3="" />
			<Param Out="" Type="4" Text1="" Text2="Michael Sahlin" Text3="" />
			<Param Out="" Type="4" Text1="" Text2="James Dillon" Text3="" />
			<Param Out="" Type="4" Text1="" Text2="Josh Yagi-Stanton" Text3="" />
			<Param Out="" Type="10" Text1="" Text2="" Text3="" />
			<Param Out="" Type="1" Text1="English Casting and Voice Recording" Text2="" Text3="" />
			<Param Out="" Type="2" Text1="" Text2="Cup of Tea Productions, Inc." Text3="" />
			<Param Out="" Type="10" Text1="" Text2="" Text3="" />
			<Param Out="" Type="1" Text1="Voice Direction" Text2="" Text3="" />
			<Param Out="" Type="3" Text1="" Text2="Patrick Seitz" Text3="" />
			<Param Out="" Type="3" Text1="" Text2="Christian LaMonte" Text3="" />
			<Param Out="" Type="10" Text1="" Text2="" Text3="" />
			<Param Out="" Type="1" Text1="Assistant Voice Direction" Text2="" Text3="" />
			<Param Out="" Type="2" Text1="" Text2="Kirsten Perotti" Text3="" />
			<Param Out="" Type="10" Text1="" Text2="" Text3="" />
			<Param Out="" Type="1" Text1="Sound Dept." Text2="" Text3="" />
			<Param Out="" Type="4" Text1="" Text2="Danni Hunt" Text3="" />
			<Param Out="" Type="4" Text1="" Text2="Daniel Bushey" Text3="" />
			<Param Out="" Type="4" Text1="" Text2="Jonathan Abarca" Text3="" />
			<Param Out="" Type="10" Text1="" Text2="" Text3="" />
			<Param Out="" Type="1" Text1="Sound Editing" Text2="" Text3="" />
			<Param Out="" Type="3" Text1="" Text2="Jean-Luc Dub" Text3="" />
			<Param Out="" Type="3" Text1="" Text2="Danni Hunt" Text3="" />
			<Param Out="" Type="10" Text1="" Text2="" Text3="" />
			<Param Out="" Type="1" Text1="Production Assistant" Text2="" Text3="" />
			<Param Out="" Type="2" Text1="" Text2="Kirsten Perotti" Text3="" />
			<Param Out="" Type="10" Text1="" Text2="" Text3="" />
			<Param Out="" Type="1" Text1="Project Manager" Text2="" Text3="" />
			<Param Out="" Type="3" Text1="" Text2="Lainie Bushey" Text3="" />
			<Param Out="" Type="3" Text1="" Text2="Danni Hunt" Text3="" />
			<Param Out="" Type="10" Text1="" Text2="" Text3="" />
			<Param Out="" Type="1" Text1="Talent Management Assistant" Text2="" Text3="" />
			<Param Out="" Type="2" Text1="" Text2="Linda Assi" Text3="" />
			<Param Out="" Type="10" Text1="" Text2="" Text3="" />
			<Param Out="" Type="1" Text1="English Vocals (Songs)" Text2="" Text3="" />
			<Param Out="" Type="3" Text1="" Text2="Barry Bach" Text3="" />
			<Param Out="" Type="3" Text1="" Text2="Katharine Eames" Text3="" />
			<Param Out="" Type="10" Text1="" Text2="" Text3="" />
			<Param Out="" Type="1" Text1="Voice Directing" Text2="" Text3="" />
			<Param Out="" Type="2" Text1="" Text2="Greg Chun" Text3="" />
			<Param Out="" Type="10" Text1="" Text2="" Text3="" />
			<Param Out="" Type="1" Text1="Vocal Engineer" Text2="" Text3="" />
			<Param Out="" Type="2" Text1="" Text2="Eddite J. Correa" Text3="" />
			<Param Out="" Type="12" Text1="" Text2="" Text3="" />
			<Param Out="" Type="8" Text1="NOE Staff" Text2="" Text3="" />
			<Param Out="" Type="1" Text1="Coordination" Text2="" Text3="" />
			<Param Out="" Type="1" Text1="(NOE, iQue, NHL, NOK)" Text2="" Text3="" />
			<Param Out="" Type="4" Text1="" Text2="Matthew Mawer" Text3="" />
			<Param Out="" Type="4" Text1="" Text2="Christian Massi" Text3="" />
			<Param Out="" Type="4" Text1="" Text2="Flavia Madonia" Text3="" />
			<Param Out="" Type="4" Text1="" Text2="Zarrah Bevan" Text3="" />
			<Param Out="" Type="4" Text1="" Text2="Roby Liebetruth" Text3="" />
			<Param Out="" Type="4" Text1="" Text2="Yuan Jun" Text3="" />
			<Param Out="" Type="4" Text1="" Text2="Sean Shen" Text3="" />
			<Param Out="" Type="4" Text1="" Text2="Natalie Yu" Text3="" />
			<Param Out="" Type="4" Text1="" Text2="Dongyeon Kim" Text3="" />
			<Param Out="" Type="4" Text1="" Text2="Jihyuen Yoo" Text3="" />
			<Param Out="" Type="10" Text1="" Text2="" Text3="" />
			<Param Out="" Type="1" Text1="Translation" Text2="" Text3="" />
			<Param Out="" Type="4" Text1="" Text2="Danielle Jorgenson-Murray" Text3="" />
			<Param Out="" Type="4" Text1="" Text2="Greg T. Sadownik" Text3="" />
			<Param Out="" Type="4" Text1="" Text2="Eren Baykal" Text3="" />
			<Param Out="" Type="4" Text1="" Text2="Matthew Fosbrook" Text3="" />
			<Param Out="" Type="4" Text1="" Text2="Sylvain Gsell" Text3="" />
			<Param Out="" Type="4" Text1="" Text2="Florence d'Anterroches" Text3="" />
			<Param Out="" Type="4" Text1="" Text2="Jean-Paul Hausmann" Text3="" />
			<Param Out="" Type="4" Text1="" Text2="Sabrina Jouillat" Text3="" />
			<Param Out="" Type="4" Text1="" Text2="Gurvan Le Guen" Text3="" />
			<Param Out="" Type="4" Text1="" Text2="Anthony Fouillen" Text3="" />
			<Param Out="" Type="4" Text1="" Text2="David Caussèque" Text3="" />
			<Param Out="" Type="4" Text1="" Text2="Claire Stalter" Text3="" />
			<Param Out="" Type="4" Text1="" Text2="Bruno Gramigna" Text3="" />
			<Param Out="" Type="4" Text1="" Text2="Valeria Castellino" Text3="" />
			<Param Out="" Type="4" Text1="" Text2="Chiara Botta" Text3="" />
			<Param Out="" Type="4" Text1="" Text2="Martina Deimel" Text3="" />
			<Param Out="" Type="4" Text1="" Text2="Alexander van de Bergh" Text3="" />
			<Param Out="" Type="4" Text1="" Text2="Sebastian Brück" Text3="" />
			<Param Out="" Type="4" Text1="" Text2="Benedikt Grosser" Text3="" />
			<Param Out="" Type="4" Text1="" Text2="Georg Schmalhofer" Text3="" />
			<Param Out="" Type="4" Text1="" Text2="Jessica Morandi" Text3="" />
			<Param Out="" Type="4" Text1="" Text2="José Manuel Malagón León" Text3="" />
			<Param Out="" Type="4" Text1="" Text2="Cristina Solà Picas" Text3="" />
			<Param Out="" Type="4" Text1="" Text2="Alfonso Díaz Jiménez" Text3="" />
			<Param Out="" Type="4" Text1="" Text2="Miguel Rodríguez Ramos" Text3="" />
			<Param Out="" Type="4" Text1="" Text2="Keywords Studios" Text3="" />
			<Param Out="" Type="10" Text1="" Text2="" Text3="" />
			<Param Out="" Type="2" Text1="" Text2="PTW Korea Co., Ltd." Text3="" />
			<Param Out="" Type="2" Text1="" Text2="DIGITAL HEARTS Co., Ltd." Text3="" />
			<Param Out="" Type="2" Text1="" Text2="DIGITAL HEARTS (Shanghai) Co., Ltd." Text3="" />
			<Param Out="" Type="10" Text1="" Text2="" Text3="" />
			<Param Out="" Type="1" Text1="Quality Assurance" Text2="" Text3="" />
			<Param Out="" Type="1" Text1="Coordination" Text2="" Text3="" />
			<Param Out="" Type="4" Text1="" Text2="Sonia Trepiccioni" Text3="" />
			<Param Out="" Type="4" Text1="" Text2="Steffen Lotz" Text3="" />
			<Param Out="" Type="4" Text1="" Text2="Yan Gang" Text3="" />
			<Param Out="" Type="4" Text1="" Text2="Umemura Eiju" Text3="" />
			<Param Out="" Type="4" Text1="" Text2="Kiung Seoung" Text3="" />
			<Param Out="" Type="4" Text1="" Text2="Keywords Studios" Text3="" />
			<Param Out="" Type="10" Text1="" Text2="" Text3="" />
			<Param Out="" Type="1" Text1="Korean" Text2="" Text3="" />
			<Param Out="" Type="2" Text1="" Text2="PTW Korea Co., Ltd." Text3="" />
			<Param Out="" Type="10" Text1="" Text2="" Text3="" />
			<Param Out="" Type="1" Text1="Chinese (Simplified and Traditional)" Text2="" Text3="" />
			<Param Out="" Type="2" Text1="" Text2="DIGITAL HEARTS Co., Ltd." Text3="" />
			<Param Out="" Type="2" Text1="" Text2="DIGITAL HEARTS (Shanghai) Co., Ltd." Text3="" />
			<Param Out="" Type="12" Text1="" Text2="" Text3="" />
			<Param Out="" Type="12" Text1="" Text2="" Text3="" />
			<Param Out="" Type="12" Text1="" Text2="" Text3="" />
			<Param Out="" Type="12" Text1="" Text2="" Text3="" />
			<Param Out="" Type="1" Text1="Project Manager" Text2="" Text3="" />
			<Param Out="" Type="2" Text1="" Text2="Akira Kinashi" Text3="" />
			<Param Out="" Type="10" Text1="" Text2="" Text3="" />
			<Param Out="" Type="1" Text1="Technical Support" Text2="" Text3="" />
			<Param Out="" Type="4" Text1="" Text2="Tomohiro Umeda" Text3="" />
			<Param Out="" Type="4" Text1="" Text2="Takehiro Oyama" Text3="" />
			<Param Out="" Type="4" Text1="" Text2="Shuhei Furukawa" Text3="" />
			<Param Out="" Type="4" Text1="" Text2="Kyohei Minato" Text3="" />
			<Param Out="" Type="4" Text1="" Text2="Hiroaki Gohara" Text3="" />
			<Param Out="" Type="10" Text1="" Text2="" Text3="" />
			<Param Out="" Type="1" Text1="Package Design" Text2="" Text3="" />
			<Param Out="" Type="4" Text1="" Text2="Jyunichi Usui" Text3="" />
			<Param Out="" Type="4" Text1="" Text2="Asuka Kaneko" Text3="" />
			<Param Out="" Type="4" Text1="" Text2="Inseon Song" Text3="" />
			<Param Out="" Type="10" Text1="" Text2="" Text3="" />
			<Param Out="" Type="12" Text1="" Text2="" Text3="" />
			<Param Out="" Type="1" Text1="Special Thanks" Text2="" Text3="" />
			<Param Out="" Type="4" Text1="" Text2="Toshio Sengoku" Text3="" />
			<Param Out="" Type="4" Text1="" Text2="Atsushi Ikuno" Text3="" />
			<Param Out="" Type="4" Text1="" Text2="Takashi Akiyama" Text3="" />
			<Param Out="" Type="4" Text1="" Text2="Tsutomu Kitanishi" Text3="" />
			<Param Out="" Type="4" Text1="" Text2="Naoki Nakano" Text3="" />
			<Param Out="" Type="4" Text1="" Text2="Naoko Mori" Text3="" />
			<Param Out="" Type="4" Text1="" Text2="Masakazu Umehara" Text3="" />
			<Param Out="" Type="4" Text1="" Text2="Kenichi Nishimaki" Text3="" />
			<Param Out="" Type="4" Text1="" Text2="Toshiyuki Kusakihara" Text3="" />
			<Param Out="" Type="4" Text1="" Text2="Kiyo Tatehata" Text3="" />
			<Param Out="" Type="10" Text1="" Text2="" Text3="" />
			<Param Out="" Type="4" Text1="" Text2="Keisuke Terasaki" Text3="" />
			<Param Out="" Type="4" Text1="" Text2="Hitoshi Yamagami" Text3="" />
			<Param Out="" Type="4" Text1="" Text2="Yurie Hattori" Text3="" />
			<Param Out="" Type="4" Text1="" Text2="Ayako Moriwaki" Text3="" />
			<Param Out="" Type="4" Text1="" Text2="Takeshi Tateishi" Text3="" />
			<Param Out="" Type="4" Text1="" Text2="Takayasu Morisawa" Text3="" />
			<Param Out="" Type="4" Text1="" Text2="Shingo Matsushita" Text3="" />
			<Param Out="" Type="2" Text1="" Text2="Communication Coordinator Group (NOE)" Text3="" />
			<Param Out="" Type="12" Text1="" Text2="" Text3="" />
			<Param Out="" Type="12" Text1="" Text2="" Text3="" />
			<Param Out="" Type="1" Text1="General Producer" Text2="" Text3="" />
			<Param Out="" Type="2" Text1="" Text2="Tohru Narihiro" Text3="" />
			<Param Out="" Type="11" Text1="" Text2="" Text3="" />
			<Param Out="" Type="1" Text1="General Producer" Text2="" Text3="" />
			<Param Out="" Type="2" Text1="" Text2="Shinya Takahashi" Text3="" />
			<Param Out="" Type="11" Text1="" Text2="" Text3="" />
			<Param Out="" Type="1" Text1="Executive Producer" Text2="" Text3="" />
			<Param Out="" Type="2" Text1="" Text2="Toshiyuki Nakamura" Text3="" />
			<Param Out="" Type="11" Text1="" Text2="" Text3="" />
			<Param Out="" Type="1" Text1="Executive Producer" Text2="" Text3="" />
			<Param Out="" Type="2" Text1="" Text2="Shuntaro Furukawa" Text3="" />
		</Data>
	</Sheet>
</Book>